Workbook
Name fa_ANYFB: Dashboard!$Q$66
Name fa_BD: Dashboard!$Q$54
Name fa_BUDGET: Dashboard!$Q$61
Name fa_CEC: Dashboard!$Q$55
Name fa_DEM: Dashboard!$Q$63
Name fa_ECe: Dashboard!$Q$41
Name fa_ECe_src: Dashboard!$Q$42
Name fa_ECgw: Dashboard!$Q$52
Name fa_ECt: Dashboard!$Q$60
Name fa_ECw: Dashboard!$Q$48
Name fa_ECw_src: Dashboard!$Q$49
Name fa_ESP: Dashboard!$Q$43
Name fa_FTEXT: Dashboard!$Q$39
Name fa_GWD: Dashboard!$Q$50
Name fa_INFIL: Dashboard!$Q$64
Name fa_K: Dashboard!$Q$53
Name fa_LIME: Dashboard!$Q$56
Name fa_LIMEHIGH: Dashboard!$Q$57
Name fa_MASTER: Dashboard!$Q$65
Name fa_NSEL: Dashboard!$Q$67
Name fa_PANS: Dashboard!$Q$40
Name fa_pH: Dashboard!$Q$46
Name fa_RESET: Dashboard!$Q$68
Name fa_RSC: Dashboard!$Q$58
Name fa_SHALLOW: Dashboard!$Q$51
Name fa_SOD: Dashboard!$Q$44
Name fa_SOD_src: Dashboard!$Q$45
Name fa_SODIC: Dashboard!$Q$47
Name fa_SOM: Dashboard!$Q$59
Name fa_TEXTURE: Dashboard!$Q$38
Name fa_TOPO: Dashboard!$Q$62
Name th_BD: Dashboard!$Q$12
Name th_ECeSLIGHT: Dashboard!$Q$6
Name th_ECgw: Dashboard!$Q$4
Name th_ECwHIGH: Dashboard!$Q$17
Name th_ECwLOW: Dashboard!$Q$16
Name th_FDEFAULT: Dashboard!$Q$20
Name th_GW: Dashboard!$Z$1
Name th_GWCRIT: Dashboard!$Q$21
Name th_K: Dashboard!$Q$11
Name th_LIME: Dashboard!$Z$2
Name th_pHCALC: Dashboard!$Q$10
Name th_pHSOD: Dashboard!$Q$9
Name th_RSC: Dashboard!$Q$14
Name th_SAL: Dashboard!$Q$5
Name th_SOD: Dashboard!$Q$7
Name th_SODHI: Dashboard!$Q$8
Name th_SOM: Dashboard!$Q$15
Name th_TDS: Dashboard!$Q$18
Name th_TOC: Dashboard!$Q$19
Name th_TOPO: Dashboard!$Q$13

Sheet Explanation
B2: Salinization Diagnosis and Measure Selection Model Overview The Salinity & Sodicity Diagnostic and Measure Selection Tool is an interactive decision-support system designed to translate raw soil, water, and groundwater data directly into actionable field interventions. Instead of requiring consultants and agronomists to manually interpret complicated laboratory reports, the model automatically determines the soil's degradation status; distinguishing between normal, saline, sodic, and saline-sodic conditions based on established international standards (Richards, 1954; Bos & Wolters, 2006). It then acts as a dynamic screening filter: it evaluates an extensive portfolio of engineering works (such as subsurface drainage and canal lining), chemical amendments (like gypsum and sulfur), and agronomic techniques against your specific field numbers. By instantly flagging dangerous management errors, such as triggering total soil structure collapse by leaching sodic soils with fresh water, and scoring options by budget class, spatial scale, and time horizon, the tool allows project teams to design realistic, cost-effective rehabilitation packages that protect both crop yield and soil permeability over the long term.
B4: Dashboard (Diagnostic Overview) The Dashboard is the automated control room and executive summary of the model, designed so that you never have to type data directly into it. It continuously reads your field numbers from Section A to determine the Master Soil Classification (Normal, Saline, Sodic, or Saline-Sodic) and evaluates the four primary risk indicators: rootzone salinity (ECe), sodicity hazard (CROSS/SAR/ESP), irrigation water salinity (ECw), and seasonal groundwater depth. It includes an audit tracker that tells you immediately whether your baseline dataset is complete or if critical measurements are still missing before you make decisions. A reset switch in cell K2 lets you toggle between active project results and a blank baseline to verify that formulas are responding properly.
B6: Section A – Field Checklist (Baseline Data Input) Section A is the dedicated input portal where you enter all raw field observations, soil surveys, and laboratory test results. It structures data by importance, starting with mandatory Priority 1 parameters: saturated paste extract salinity (ECe), sodium hazard ratios, irrigation water salinity, and groundwater table depth. If full laboratory data is not yet available, the sheet accepts practical field screening fallbacks (such as EC1:5 extracts or water TDS readings) and automatically applies texture-based conversion factors. It also records secondary soil properties, including permeability (K), topsoil pH, lime content (CaCO3), and regional climate data. Because every calculation across the entire workbook references these input rows, accurate data entry here controls the quality of the entire diagnosis.
B8: Section B – Classification 1 (Diagnostic Criteria & Soil Mechanics) Section B serves as the scientific reference engine that translates raw measured numbers into physical soil diagnoses. It provides standard benchmark tables for soil salinity classes, sodium adsorption boundaries, infiltration risks, and drainage criteria. Beyond classification, it explains the physical mechanics behind soil degradation, such as clay swelling, aggregate breakdown, and surface crusting caused by high exchangeable sodium. Importantly, it highlights critical management rules, such as warning against the "leaching trap"; the costly mistake of flushing a sodic soil with fresh water before adding calcium amendments, which causes complete collapse of soil structure.
B10: Section C – Measure Selection (Intervention Matrix) Section C is an interactive action matrix containing an extensive library of engineering, chemical, and agronomic management measures. It covers physical interventions (such as subsurface pipe drainage, open ditches, and canal lining), chemical amendments (like gypsum and sulfur applications), and biological adaptations (including green manuring, mulching, and salt-tolerant crop varieties). A dynamic indicator automatically compares each measure against your site diagnosis from Section A, instantly flagging options as recommended, requiring more site data, or dangerous under current field conditions. Planners can use the final dropdown column to select and package feasible interventions for advisory reports, cost-benefit analyses, and field execution plans.
B12: Section D – Classification 2 (Criteria Glossary & Framework Definitions) Section D is the reference guide and terminology dictionary that defines the evaluation criteria used in Section C. It outlines the operational boundaries for Strategic Goals (distinguishing between preventive action, ongoing mitigation, active soil remediation, and long-term crop adaptation). It also standardizes Budget Classes (ranging from low-cost farm inputs under $250/ha to major public infrastructure exceeding $2,000/ha), Spatial Scales (individual farm holdings versus regional irrigation districts), and Time Horizons (immediate relief versus multi-year investments). By establishing clear definitions for operational complexity and environmental risks (such as the disposal of saline drainage water), this sheet ensures project teams and stakeholders interpret recommendations consistently.

Sheet Dashboard
B1: SALINITY & SODICITY DIAGNOSTIC DASHBOARD | P1: CALCULATION ENGINE (helper cells behind the fa_* and th_* names) | Z1: 2
B2: All results are driven by Section A. Nothing on this sheet is typed in by hand except the reset control. | I2: RESET | K2: LIVE (normal use) | P2: Edit only the shaded threshold and factor cells. Everything else is formula-driven. | Z2: 2
B3: =IF(fa_RESET=1,"RESET IS ON: every result below is blanked and every measure tick is ignored. Set K2 back to LIVE to restore them, or clear Section A columns E and F and Section C column P to erase the data permanently.","") | P3: THRESHOLDS
B4: A | DIAGNOSIS | P4: th_ECgw | Q4: 1.5 | R4: Saline groundwater if ECgw is at or above this (dS/m). Section B Table 11; Bhutta & Smedema (2007).
B5: MASTER SOIL CLASSIFICATION | P5: th_SAL | Q5: 4 | R5: Saline soil if ECe is at or above this (dS/m). Richards (1954).
B6: =fa_MASTER -> Insufficient data | P6: th_ECeSLIGHT | Q6: 2 | R6: Lower bound of 'slightly saline', ECe (dS/m). Richards (1954).
B7: =IF(fa_MASTER="Insufficient data","Needs ECe (or EC1:5) and CROSS, SAR or ESP","ECe "&ROUND(fa_ECe,1)&" | "&IF(fa_SOD="","CROSS/SAR/ESP not measured",IF(fa_SOD_src="ESP","SAR-eq.",fa_SOD_src)&" "&ROUND(fa_SOD,1))&" | pH "&IF(fa_pH="","n/a",ROUND(fa_pH,1))) -> Needs ECe (or EC1:5) and CROSS, SAR or ESP | P7: th_SOD | Q7: 13 | R7: Sodic if CROSS/SAR is at or above this. Richards (1954); Rengasamy & Marchuk (2011).
B8: =IF(AND(fa_SOD="",fa_RESET=0),IF(fa_SODIC=1,"Indicative only: pH above "&ROUND(th_pHSOD,1)&" suggests a sodic soil, but pH is not an official sodicity criterion. Measure CROSS, SAR or ESP to confirm.","Not possible to say whether the soil is sodic: CROSS, SAR or ESP is missing and "&IF(fa_pH="","pH is not measured either.","pH "&ROUND(fa_pH,1)&" ("&IF(fa_pH<7.5,"acidic to neutral","slightly alkaline")&") is not conclusive.")),IF(fa_MASTER="Insufficient data","[Complete the Priority 1 inputs]",IF(AND(fa_SODIC=0,ISNUMBER(fa_pH),fa_pH>th_pHSOD),"Not sodic: the measured "&fa_SOD_src&" decides. pH "&ROUND(fa_pH,1)&" is unusually high for a non-sodic soil, so re-check the sample or lab result.",IF(fa_ANYFB=1,"(Screening level: based on fallback data)","[All metrics from Primary methods]")))) -> Not possible to say whether the soil is sodic: CROSS, SAR or ESP is missing and pH is not measured either. | P8: th_SODHI | Q8: 9 | R8: Lower bound of 'High Hazard' sodicity (CROSS/SAR). Project brief.
P9: th_pHSOD | Q9: 8.5 | R9: Sodic / free Na2CO3 if soil pH is above this. Richards (1954).
B10: P1 SOIL SALINITY (ECe) | E10: P1 SODICITY (CROSS / SAR / ESP) | H10: P1 IRRIGATION WATER (ECw) | K10: P1 GROUNDWATER DEPTH | P10: th_pHCALC | Q10: 7.8 | R10: Calcareous / alkaline if soil pH is at or above this. Project brief.
B11: =IF(fa_ECe="","NOT MEASURED",IF(fa_ECe<th_ECeSLIGHT,"Non-saline",IF(fa_ECe<th_SAL,"Slightly saline",IF(fa_ECe<8,"Moderately saline",IF(fa_ECe<=16,"Strongly saline","Very strongly saline"))))) -> NOT MEASURED | E11: =IF(fa_SOD="","NOT MEASURED",IF(fa_SOD_src="SAR",IF(fa_SOD<13,"Non-Sodic","Sodic (Alkali)"),IF(fa_SOD_src="ESP",IF(fa_ESP<15,"Non-Sodic",IF(fa_ESP<=30,"Moderately Sodic","Severely Sodic")),IF(fa_SOD_src="CROSS",IF(fa_SOD<13,"Non-Sodic",IF(fa_SOD<=20,"Moderately Sodic","Severely Sodic")),"Unknown Class")))) -> NOT MEASURED | H11: =IF(fa_ECw="","NOT MEASURED",IF(fa_ECw<th_ECwLOW,"No restriction",IF(fa_ECw<=th_ECwHIGH,"Slight to moderate restriction","Severe restriction"))) -> NOT MEASURED | K11: =IF(fa_GWD="","NOT MEASURED",IF(fa_GWD>th_GW,"Safe depth",IF(fa_GWD>=th_GWCRIT,"Moderate risk","Critical (waterlogged)"))) -> NOT MEASURED | P11: th_K | Q11: 0.15 | R11: Subsoil K (m/day) below this is restrictive for pipe drainage. Project brief.
B12: =IF(fa_ECe_src="Primary","[Method: Primary ECe]",IF(fa_ECe_src="Fallback","[Fallback: EC1:5] f = "&ROUND(fa_FTEXT,1)&" ("&IF(fa_TEXTURE="","texture blank, loam assumed",fa_TEXTURE)&")","[No input: enter ECe or EC1:5]")) -> [No input: enter ECe or EC1:5] | E12: =IF(fa_SOD_src="CROSS","[Primary: CROSS]",IF(fa_SOD_src="SAR","[Fallback: SAR]",IF(fa_SOD_src="ESP","[Fallback: ESP] converted to SAR-eq. (Richards 1954)","[No input: enter CROSS, SAR or ESP]"))) -> [No input: enter CROSS, SAR or ESP] | H12: =IF(fa_ECw_src="Primary","[Method: Primary ECw]",IF(fa_ECw_src="Fallback","[Fallback: TDS / "&ROUND(th_TDS,0)&"]","[No input: enter ECw or TDS]")) -> [No input: enter ECw or TDS] | K12: =IF(fa_GWD="","[No input: enter groundwater depth]","[Method: Primary piezometer reading]") -> [No input: enter groundwater depth] | P12: th_BD | Q12: 1.5 | R12: Bulk density (g/cm3) above this triggers subsoiling. Project brief.
B13: P3 Soil pH (supporting) | E13: =IF(fa_pH="","NOT MEASURED",IF(fa_pH<6.5,"Acidic",IF(fa_pH<th_pHCALC,"Neutral / Optimal",IF(fa_pH<=th_pHSOD,"Calcareous / Alkaline","Strongly Alkaline / Free Na2CO3")))) -> NOT MEASURED | H13: pH above 8.5 only suggests sodicity: it is not an official criterion and does not replace a CROSS, SAR or ESP measurement. It is a Priority 3 input in this model. | P13: th_TOPO | Q13: 3 | R13: Micro-topography variance (cm) above this triggers laser leveling. Project brief.
P14: th_RSC | Q14: 1.25 | R14: Irrigation water RSC (meq/L) above this. Eaton (1950); Section B Table 18.
B15: B | BASELINE COMPLETENESS AND WHAT IS STILL MISSING | P15: th_SOM | Q15: 1.5 | R15: Soil organic matter (%) below this is low. Project brief.
B16: =IF(COUNTIF($I$20:$I$23,"MISSING - CRITICAL")=0,"BASELINE COMPLETE","BASELINE INCOMPLETE") -> BASELINE INCOMPLETE | F16: =(4-COUNTIF($I$20:$I$23,"MISSING - CRITICAL"))&" of 4 Priority-1 parameters available | "&COUNTIF($I$27:$I$38,"MISSING - REQUIRED")&" conditional parameter(s) now required | "&COUNTIF($I$27:$I$38,"Not measured")&" optional parameter(s) not measured" -> 0 of 4 Priority-1 parameters available | 0 conditional parameter(s) now required | 12 optional parameter(s) not measured | P16: th_ECwLOW | Q16: 0.7 | R16: ECw (dS/m) above which use restriction starts. Ayers & Westcot (1985).
B17: Priority 1 is the minimum the soil classification needs. Priority 2 to 4 are only required once the diagnosis calls for them, which is what the audit status column says. | P17: th_ECwHIGH | Q17: 3 | R17: ECw (dS/m) above which use restriction is severe. Ayers & Westcot (1985).
B18: Tier 1 | Priority 1, mandatory baseline | P18: th_TDS | Q18: 640 | R18: Divisor from TDS (mg/L) to ECw (dS/m). Section A row 'TDS'; Section B Table 9.
B19: Prio | C19: Parameter | E19: Primary | F19: Fallback | G19: Data source | I19: Audit status | K19: Why it is needed | P19: th_TOC | Q19: 1.724 | R19: Multiplier from TOC (%) to SOM (%). Section A row 'TOC'.
B20: P1 | C20: Soil Salinity (ECe or EC1:5) | E20: =IF(ISNUMBER('Section A - Field Checklist'!$H$5),'Section A - Field Checklist'!$H$5,"-") -> - | F20: =IF(ISNUMBER('Section A - Field Checklist'!$H$6),'Section A - Field Checklist'!$H$6,"-") -> - | G20: =IF(ISNUMBER('Section A - Field Checklist'!$H$5),"Primary",IF(ISNUMBER('Section A - Field Checklist'!$H$6),"Fallback","Missing")) -> Missing | I20: =IF(G20="Missing","MISSING - CRITICAL",IF(G20="Fallback","OK (fallback, confirm in lab)","OK")) -> MISSING - CRITICAL | K20: Sets the salinity class and the leaching requirement. Without it there is no soil classification at all. | P20: th_FDEFAULT | Q20: 9.5 | R20: EC1:5 to ECe factor used when texture is blank (loam). Slavich & Petterson (1993).
B21: P1 | C21: Sodicity (CROSS or SAR / ESP) | E21: =IF(ISNUMBER('Section A - Field Checklist'!$H$7),'Section A - Field Checklist'!$H$7,"-") -> - | F21: =IF(ISNUMBER('Section A - Field Checklist'!$H$8),"SAR "&'Section A - Field Checklist'!$H$8,IF(ISNUMBER('Section A - Field Checklist'!$H$9),"ESP "&'Section A - Field Checklist'!$H$9&"%","-")) -> - | G21: =IF(ISNUMBER('Section A - Field Checklist'!$H$7),"Primary",IF(OR(ISNUMBER('Section A - Field Checklist'!$H$8),ISNUMBER('Section A - Field Checklist'!$H$9)),"Fallback","Missing")) -> Missing | I21: =IF(G21="Missing","MISSING - CRITICAL",IF(G21="Fallback","OK (fallback, confirm in lab)","OK")) -> MISSING - CRITICAL | K21: Decides whether leaching is safe. A sodic soil has to receive calcium before any fresh water is applied. | P21: th_GWCRIT | Q21: 1.5 | R21: Water table (m) below this is critical / waterlogged. Section B Table 10; Ritzema (1994).
B22: P1 | C22: Irrigation Water Salinity (ECw or TDS) | E22: =IF(ISNUMBER('Section A - Field Checklist'!$H$10),'Section A - Field Checklist'!$H$10,"-") -> - | F22: =IF(ISNUMBER('Section A - Field Checklist'!$H$11),'Section A - Field Checklist'!$H$11,"-") -> - | G22: =IF(ISNUMBER('Section A - Field Checklist'!$H$10),"Primary",IF(ISNUMBER('Section A - Field Checklist'!$H$11),"Fallback","Missing")) -> Missing | I22: =IF(G22="Missing","MISSING - CRITICAL",IF(G22="Fallback","OK (fallback, confirm in lab)","OK")) -> MISSING - CRITICAL | K22: Gives the salt load added with every irrigation and the leaching fraction needed to keep the balance. | P22: EC1:5 TO ECe TEXTURE FACTORS (Slavich & Petterson 1993)
B23: P1 | C23: Groundwater Depth | E23: =IF(ISNUMBER('Section A - Field Checklist'!$H$12),'Section A - Field Checklist'!$H$12,"-") -> - | F23: n/a | G23: =IF(ISNUMBER('Section A - Field Checklist'!$H$12),"Primary","Missing") -> Missing | I23: =IF(G23="Missing","MISSING - CRITICAL",IF(G23="Fallback","OK (fallback, confirm in lab)","OK")) -> MISSING - CRITICAL | K23: A water table above 2.0 m drives capillary rise and decides whether drainage is needed at all. | P23: Texture keyword | Q23: Factor f | R23: Keyword found in texture input?
P24: heavy clay | Q24: 5.8 | R24: =IF(fa_TEXTURE="",FALSE(),ISNUMBER(SEARCH(P24,fa_TEXTURE))) -> FALSE
B25: Tier 2 | Priority 2, 3 and 4, conditional and secondary | P25: medium clay | Q25: 7.5 | R25: =IF(fa_TEXTURE="",FALSE(),ISNUMBER(SEARCH(P25,fa_TEXTURE))) -> FALSE
B26: Prio | C26: Parameter | E26: Primary | F26: Fallback | G26: Data source | I26: Audit status | K26: Why it is needed | P26: sandy clay loam | Q26: 9.5 | R26: =IF(fa_TEXTURE="",FALSE(),ISNUMBER(SEARCH(P26,fa_TEXTURE))) -> FALSE
B27: P2 | C27: Hydraulic Conductivity (K) | E27: =IF(ISNUMBER('Section A - Field Checklist'!$H$15),'Section A - Field Checklist'!$H$15,"-") -> - | F27: =IF(ISNUMBER('Section A - Field Checklist'!$H$16),'Section A - Field Checklist'!$H$16,"-") -> - | G27: =IF(ISNUMBER('Section A - Field Checklist'!$H$15),"Primary",IF(ISNUMBER('Section A - Field Checklist'!$H$16),"Fallback","Missing")) -> Missing | I27: =IF(G27<>"Missing",IF(G27="Fallback","OK (fallback)","OK"),IF(fa_SHALLOW=1,"MISSING - REQUIRED","Not measured")) -> Not measured | K27: Sets the drain spacing (Hooghoudt). Required as soon as a shallow water table makes drainage necessary. | P27: clay loam | Q27: 8.6 | R27: =IF(fa_TEXTURE="",FALSE(),ISNUMBER(SEARCH(P27,fa_TEXTURE))) -> FALSE
B28: P2 | C28: Soil Texture & Layering | E28: =IF(AND(LEN(TRIM('Section A - Field Checklist'!$H$17&""))>0,LOWER(TRIM('Section A - Field Checklist'!$H$17&""))<>"unknown"),'Section A - Field Checklist'!$H$17,"-") -> - | F28: =IF(AND(LEN(TRIM('Section A - Field Checklist'!$H$18&""))>0,LOWER(TRIM('Section A - Field Checklist'!$H$18&""))<>"unknown"),'Section A - Field Checklist'!$H$18,"-") -> - | G28: =IF(AND(LEN(TRIM('Section A - Field Checklist'!$H$17&""))>0,LOWER(TRIM('Section A - Field Checklist'!$H$17&""))<>"unknown"),"Primary",IF(AND(LEN(TRIM('Section A - Field Checklist'!$H$18&""))>0,LOWER(TRIM('Section A - Field Checklist'!$H$18&""))<>"unknown"),"Fallback","Missing")) -> Missing | I28: =IF(G28<>"Missing",IF(G28="Fallback","OK (fallback)","OK"),IF(fa_ECe_src="Fallback","MISSING - REQUIRED","Not measured")) -> Not measured | K28: Supplies the EC1:5 to ECe factor and reveals clay or plough pans that block vertical flow. | P28: sandy clay | Q28: 8.6 | R28: =IF(fa_TEXTURE="",FALSE(),ISNUMBER(SEARCH(P28,fa_TEXTURE))) -> FALSE
B29: P2 | C29: Micro-topography & Slope | E29: =IF(ISNUMBER('Section A - Field Checklist'!$H$19),'Section A - Field Checklist'!$H$19,"-") -> - | F29: =IF(AND(LEN(TRIM('Section A - Field Checklist'!$H$20&""))>0,LOWER(TRIM('Section A - Field Checklist'!$H$20&""))<>"unknown"),'Section A - Field Checklist'!$H$20,"-") -> - | G29: =IF(ISNUMBER('Section A - Field Checklist'!$H$19),"Primary",IF(ISNUMBER('Section A - Field Checklist'!$H$20),"Fallback","Missing")) -> Missing | I29: =IF(G29<>"Missing",IF(G29="Fallback","OK (fallback)","OK"),"Not measured") -> Not measured | K29: Shows the low spots that waterlog and the high spots where salt scalds appear. Basis for land leveling. | P29: silty clay | Q29: 8.6 | R29: =IF(fa_TEXTURE="",FALSE(),ISNUMBER(SEARCH(P29,fa_TEXTURE))) -> FALSE
B30: P3 | C30: Cation Exchange Capacity (CEC) | E30: =IF(ISNUMBER('Section A - Field Checklist'!$H$23),'Section A - Field Checklist'!$H$23,"-") -> - | F30: =IF(ISNUMBER('Section A - Field Checklist'!$H$24),'Section A - Field Checklist'!$H$24,"-") -> - | G30: =IF(ISNUMBER('Section A - Field Checklist'!$H$23),"Primary",IF(ISNUMBER('Section A - Field Checklist'!$H$24),"Fallback","Missing")) -> Missing | I30: =IF(G30<>"Missing",IF(G30="Fallback","OK (fallback)","OK"),IF(fa_SODIC=1,"MISSING - REQUIRED","Not measured")) -> Not measured | K30: Multiplier in the gypsum requirement. Without it the dose for a sodic soil cannot be quantified. | P30: light clay | Q30: 8.6 | R30: =IF(fa_TEXTURE="",FALSE(),ISNUMBER(SEARCH(P30,fa_TEXTURE))) -> FALSE
B31: P3 | C31: Soil Bulk Density | E31: =IF(ISNUMBER('Section A - Field Checklist'!$H$25),'Section A - Field Checklist'!$H$25,"-") -> - | F31: =IF(ISNUMBER('Section A - Field Checklist'!$H$26),'Section A - Field Checklist'!$H$26,"-") -> - | G31: =IF(ISNUMBER('Section A - Field Checklist'!$H$25),"Primary",IF(ISNUMBER('Section A - Field Checklist'!$H$26),"Fallback","Missing")) -> Missing | I31: =IF(G31<>"Missing",IF(G31="Fallback","OK (fallback)","OK"),IF(fa_SODIC=1,"MISSING - REQUIRED","Not measured")) -> Not measured | K31: Converts the gypsum requirement from a mass basis to tonnes per hectare over the reclamation depth. | P31: clay | Q31: 7.5 | R31: =IF(fa_TEXTURE="",FALSE(),ISNUMBER(SEARCH(P31,fa_TEXTURE))) -> FALSE
B32: P3 | C32: Native Lime (CaCO3) | E32: =IF(ISNUMBER('Section A - Field Checklist'!$H$27),'Section A - Field Checklist'!$H$27,"-") -> - | F32: =IF(AND(LEN(TRIM('Section A - Field Checklist'!$H$28&""))>0,LOWER(TRIM('Section A - Field Checklist'!$H$28&""))<>"unknown"),'Section A - Field Checklist'!$H$28,"-") -> - | G32: =IF(ISNUMBER('Section A - Field Checklist'!$H$27),"Primary",IF(AND(LEN(TRIM('Section A - Field Checklist'!$H$28&""))>0,LOWER(TRIM('Section A - Field Checklist'!$H$28&""))<>"unknown"),"Fallback","Missing")) -> Missing | I32: =IF(G32<>"Missing",IF(G32="Fallback","OK (fallback)","OK"),IF(fa_SODIC=1,"MISSING - REQUIRED","Not measured")) -> Not measured | K32: Decides whether cheap sulfur or acid can replace imported gypsum on a calcareous sodic soil. | P32: sandy loam | Q32: 14 | R32: =IF(fa_TEXTURE="",FALSE(),ISNUMBER(SEARCH(P32,fa_TEXTURE))) -> FALSE
B33: P3 | C33: Carbonate Risk (RSC / SARadj) | E33: =IF(ISNUMBER('Section A - Field Checklist'!$H$29),'Section A - Field Checklist'!$H$29,"-") -> - | F33: =IF(ISNUMBER('Section A - Field Checklist'!$H$30),'Section A - Field Checklist'!$H$30,"-") -> - | G33: =IF(ISNUMBER('Section A - Field Checklist'!$H$29),"Primary",IF(ISNUMBER('Section A - Field Checklist'!$H$30),"Fallback","Missing")) -> Missing | I33: =IF(G33<>"Missing",IF(G33="Fallback","OK (fallback)","OK"),"Not measured") -> Not measured | K33: Flags bicarbonate precipitation, which removes Ca and Mg from the water and raises the effective SAR. | P33: sand | Q33: 23 | R33: =IF(fa_TEXTURE="",FALSE(),ISNUMBER(SEARCH(P33,fa_TEXTURE))) -> FALSE
B34: P3 | C34: Soil pH | E34: =IF(ISNUMBER('Section A - Field Checklist'!$H$31),'Section A - Field Checklist'!$H$31,"-") -> - | F34: n/a | G34: =IF(ISNUMBER('Section A - Field Checklist'!$H$31),"Primary","Missing") -> Missing | I34: =IF(G34<>"Missing",IF(G34="Fallback","OK (fallback)","OK"),IF(fa_SODIC=1,"MISSING - REQUIRED","Not measured")) -> Not measured | K34: Confirms free Na2CO3 above 8.5 and tells whether the acid route to reclamation is open. | P34: silt | Q34: 9.5 | R34: =IF(fa_TEXTURE="",FALSE(),ISNUMBER(SEARCH(P34,fa_TEXTURE))) -> FALSE
B35: P3 | C35: Groundwater Salinity (ECgw) | E35: =IF(ISNUMBER('Section A - Field Checklist'!$H$32),'Section A - Field Checklist'!$H$32,"-") -> - | F35: n/a | G35: =IF(ISNUMBER('Section A - Field Checklist'!$H$32),"Primary","Missing") -> Missing | I35: =IF(G35<>"Missing",IF(G35="Fallback","OK (fallback)","OK"),IF(fa_SHALLOW=1,"MISSING - REQUIRED","Not measured")) -> Not measured | K35: Separates capillary salinization from plain waterlogging. Required whenever the water table is shallow. | P35: loam | Q35: 9.5 | R35: =IF(fa_TEXTURE="",FALSE(),ISNUMBER(SEARCH(P35,fa_TEXTURE))) -> FALSE
B36: P4 | C36: Soil Organic Matter (SOM / TOC) | E36: =IF(ISNUMBER('Section A - Field Checklist'!$H$35),'Section A - Field Checklist'!$H$35,"-") -> - | F36: =IF(ISNUMBER('Section A - Field Checklist'!$H$36),'Section A - Field Checklist'!$H$36,"-") -> - | G36: =IF(ISNUMBER('Section A - Field Checklist'!$H$35),"Primary",IF(ISNUMBER('Section A - Field Checklist'!$H$36),"Fallback","Missing")) -> Missing | I36: =IF(G36<>"Missing",IF(G36="Fallback","OK (fallback)","OK"),"Not measured") -> Not measured | K36: Organic matter holds the structure together against dispersion and supports every other measure.
B37: P4 | C37: Crop Salt Tolerance (ECt) | E37: =IF(ISNUMBER('Section A - Field Checklist'!$H$37),'Section A - Field Checklist'!$H$37,"-") -> - | F37: =IF(AND(LEN(TRIM('Section A - Field Checklist'!$H$38&""))>0,LOWER(TRIM('Section A - Field Checklist'!$H$38&""))<>"unknown"),'Section A - Field Checklist'!$H$38,"-") -> - | G37: =IF(ISNUMBER('Section A - Field Checklist'!$H$37),"Primary",IF(ISNUMBER('Section A - Field Checklist'!$H$38),"Fallback","Missing")) -> Missing | I37: =IF(G37<>"Missing",IF(G37="Fallback","OK (fallback)","OK"),"Not measured") -> Not measured | K37: Threshold below which yield is unaffected. Needed to set the minimum leaching requirement. | P37: ACTIVE VALUES (Primary first, then Fallback)
B38: P4 | C38: Capital & Budget | E38: =IF(AND(LEN(TRIM('Section A - Field Checklist'!$H$39&""))>0,LOWER(TRIM('Section A - Field Checklist'!$H$39&""))<>"unknown"),'Section A - Field Checklist'!$H$39,"-") -> - | F38: n/a | G38: =IF(AND(LEN(TRIM('Section A - Field Checklist'!$H$39&""))>0,LOWER(TRIM('Section A - Field Checklist'!$H$39&""))<>"unknown"),"Primary","Missing") -> Missing | I38: =IF(G38<>"Missing",IF(G38="Fallback","OK (fallback)","OK"),"Not measured") -> Not measured | K38: Decides whether high-capital drainage or low-capital agronomy is the realistic route. | P38: fa_TEXTURE | Q38: =IF(AND(LEN(TRIM('Section A - Field Checklist'!$H$17&""))>0,LOWER(TRIM('Section A - Field Checklist'!$H$17&""))<>"unknown"),TRIM('Section A - Field Checklist'!$H$17&""),IF(AND(LEN(TRIM('Section A - Field Checklist'!$H$18&""))>0,LOWER(TRIM('Section A - Field Checklist'!$H$18&""))<>"unknown"),TRIM('Section A - Field Checklist'!$H$18&""),"")) | R38: Texture text: lab class, else hand test.
P39: fa_FTEXT | Q39: =IF(fa_TEXTURE="",th_FDEFAULT,IFERROR(INDEX($Q$24:$Q$35,MATCH(TRUE(),$R$24:$R$35,0)),th_FDEFAULT)) -> 9.5 | R39: EC1:5 to ECe factor for the texture (first keyword match; loam if none).
B40: C | WARNINGS AND CROSS-PARAMETER CHECKS | P40: fa_PANS | Q40: =IF(OR(ISNUMBER(SEARCH("pan",'Section A - Field Checklist'!$H$17&" "&'Section A - Field Checklist'!$H$18)),ISNUMBER(SEARCH("stratif",'Section A - Field Checklist'!$H$17&" "&'Section A - Field Checklist'!$H$18))),1,0) -> 0 | R40: 1 if either texture entry mentions a pan or stratified layer (Section B Table 13).
B41: =IF(COUNTIF($E$43:$E$47,"CRITICAL")>0,COUNTIF($E$43:$E$47,"CRITICAL")&" CRITICAL item(s) below. Read these before selecting any measure.",IF(COUNTIF($E$43:$E$47,"WARNING")>0,COUNTIF($E$43:$E$47,"WARNING")&" WARNING(s) below.",IF(COUNTIF($E$43:$E$47,"DATA NEEDED")>0,"No critical warnings yet. Some checks are still waiting for data.","All cross-parameter checks are CLEAR."))) -> No critical warnings yet. Some checks are still waiting for data. | P41: fa_ECe | Q41: =IF(ISNUMBER('Section A - Field Checklist'!$H$5),'Section A - Field Checklist'!$H$5,IF(ISNUMBER('Section A - Field Checklist'!$H$6),'Section A - Field Checklist'!$H$6*fa_FTEXT,"")) | R41: Active ECe (dS/m): saturated paste, else EC1:5 x texture factor.
B42: Check | E42: Status | G42: Finding and required action | P42: fa_ECe_src | Q42: =IF(ISNUMBER('Section A - Field Checklist'!$H$5),"Primary",IF(ISNUMBER('Section A - Field Checklist'!$H$6),"Fallback","")) | R42: Source of active ECe.
B43: Shallow groundwater risk | E43: =IF(fa_SHALLOW="","DATA NEEDED",IF(fa_SHALLOW=0,"CLEAR",IF(fa_ECgw="","WARNING",IF(fa_ECgw>=th_ECgw,"CRITICAL","WARNING")))) -> DATA NEEDED | G43: =IF(fa_SHALLOW="","Groundwater depth not measured: capillary salinization and waterlogging cannot be assessed.",IF(fa_SHALLOW=0,"Groundwater at "&ROUND(fa_GWD,2)&" m lies below the critical depth ("&ROUND(th_GW,2)&" m). No capillary or waterlogging hazard at screening level.",IF(fa_ECgw="","Shallow groundwater ("&ROUND(fa_GWD,2)&" m) of unknown salinity. Measure ECgw to separate capillary salinization from waterlogging.",IF(fa_ECgw>=th_ECgw,"SHALLOW SALINE GROUNDWATER: water table at "&ROUND(fa_GWD,2)&" m with ECgw "&ROUND(fa_ECgw,1)&" dS/m. Capillary rise will salinize the root zone. Lower the water table with subsurface pipe drainage.","SHALLOW FRESH GROUNDWATER: water table at "&ROUND(fa_GWD,2)&" m with ECgw "&ROUND(fa_ECgw,1)&" dS/m. The risk is waterlogging and root-zone anoxia, not salinization. Prioritise surface water removal (open ditches, field outlets).")))) -> Groundwater depth not measured: capillary salinization and waterlogging cannot be assessed. | P43: fa_ESP | Q43: =IF(ISNUMBER('Section A - Field Checklist'!$H$9),'Section A - Field Checklist'!$H$9,"") | R43: ESP as entered (%).
B44: Sodic Leaching Trap | E44: =IF(AND(ISNUMBER(fa_ECe),fa_ECe>=th_SAL,fa_SODIC=1),"CRITICAL",IF(fa_SODIC=1,"WARNING",IF(OR(fa_ECe="",fa_SODIC=""),"DATA NEEDED","CLEAR"))) -> DATA NEEDED | G44: =IF(AND(ISNUMBER(fa_ECe),fa_ECe>=th_SAL,fa_SODIC=1),IF(fa_SOD="","Probably saline-sodic (pH only, CROSS/SAR not measured). Do not leach with fresh water until gypsum has been applied or a CROSS/SAR measurement rules out sodicity.","CRITICAL RECLAMATION WARNING: Saline-Sodic soil diagnosed. DO NOT LEACH WITH FRESHWATER! Desalinizing before desodification removes stabilizing electrolytes, triggering immediate clay swelling, dispersion, and macropore sealing. "&"Incorporate calcium amendments (Gypsum) prior to leaching."),IF(fa_SODIC=1,IF(fa_SOD="","Probably sodic (pH only, CROSS/SAR not measured). Treat it as sodic until measured: no leaching with fresh water before a calcium amendment.","Sodic soil: leaching or heavy irrigation with fresh water will disperse the clay. Apply a calcium amendment before any leaching."),IF(OR(fa_ECe="",fa_SODIC=""),"Salinity or sodicity data missing: leaching safety cannot be confirmed.","Soil is not sodic: salts can be leached safely, provided drainage is adequate."))) -> Salinity or sodicity data missing: leaching safety cannot be confirmed. | P44: fa_SOD | Q44: =IF(ISNUMBER('Section A - Field Checklist'!$H$7),'Section A - Field Checklist'!$H$7,IF(ISNUMBER('Section A - Field Checklist'!$H$8),'Section A - Field Checklist'!$H$8,IF(AND(ISNUMBER('Section A - Field Checklist'!$H$9),'Section A - Field Checklist'!$H$9<100),('Section A - Field Checklist'!$H$9/(100-'Section A - Field Checklist'!$H$9)+0.0126)/0.01475,""))) | R44: Active sodicity index: CROSS, else SAR, else ESP converted to SAR-equivalent with the USSL relation ESR = -0.0126 + 0.01475 SAR (Richards 1954).
B45: Infiltration risk (ECw vs. CROSS/SAR) | E45: =IF(fa_INFIL="","DATA NEEDED",CHOOSE(fa_INFIL+1,"CLEAR","WARNING","CRITICAL")) -> DATA NEEDED | G45: =IF(fa_INFIL="","ECw or CROSS/SAR missing: the infiltration hazard cannot be assessed.",CHOOSE(fa_INFIL+1,"No infiltration restriction expected (FAO 29, Section B Table 22): ECw "&ROUND(fa_ECw,1)&" dS/m is sufficient for CROSS/SAR "&ROUND(fa_SOD,1)&".","Slight to moderate infiltration restriction (FAO 29, Section B Table 22): ECw "&ROUND(fa_ECw,1)&" dS/m has too few electrolytes for CROSS/SAR "&ROUND(fa_SOD,1)&". Expect surface crusting and slower permeability; consider gypsum or acid dosing of the irrigation water.","SEVERE infiltration restriction (FAO 29, Section B Table 22): ECw "&ROUND(fa_ECw,1)&" dS/m cannot keep a soil with CROSS/SAR "&ROUND(fa_SOD,1)&" flocculated. Surface crusting and permeability collapse are likely; dose gypsum into the water or onto the soil surface.")) -> ECw or CROSS/SAR missing: the infiltration hazard cannot be assessed. | P45: fa_SOD_src | Q45: =IF(ISNUMBER('Section A - Field Checklist'!$H$7),"CROSS",IF(ISNUMBER('Section A - Field Checklist'!$H$8),"SAR",IF(ISNUMBER('Section A - Field Checklist'!$H$9),"ESP",""))) | R45: Source of active sodicity.
B46: Sulfur/acid instead of gypsum | E46: =IF(fa_SODIC="","DATA NEEDED",IF(fa_SODIC=0,"CLEAR",IF(fa_SOD="","DATA NEEDED",IF(fa_LIMEHIGH="","DATA NEEDED",IF(AND(fa_LIMEHIGH=1,ISNUMBER(fa_pH),fa_pH>=th_pHCALC),"OPPORTUNITY","CLEAR"))))) -> DATA NEEDED | G46: =IF(fa_SODIC="","Sodicity not determined.",IF(fa_SODIC=0,"Soil is not sodic: no reclamation amendment required.",IF(fa_SOD="","Sodicity is only presumed from pH: measure CROSS/SAR before choosing sulfur/acid over gypsum. Until then gypsum is the provisional choice.",IF(fa_LIMEHIGH="","Soil is sodic but native lime is not measured: the sulfur/acid alternative to gypsum cannot be evaluated.",IF(fa_LIMEHIGH=0,"Native lime below "&ROUND(th_LIME,1)&"%: gypsum is the calcium source; acidifying amendments are not suitable.",IF(AND(ISNUMBER(fa_pH),fa_pH>=th_pHCALC),"Calcareous sodic soil ("&IF(ISNUMBER(fa_LIME),"CaCO3 "&ROUND(fa_LIME,1)&"%","lime-rich by HCl test")&", pH "&ROUND(fa_pH,1)&"): elemental sulfur or acid can dissolve native lime and release Ca2+ in situ, a significant saving compared with imported gypsum.","Native lime is present, but pH is below "&ROUND(th_pHCALC,1)&" or not measured: confirm pH before choosing the acid route.")))))) -> Sodicity not determined. | P46: fa_pH | Q46: =IF(ISNUMBER('Section A - Field Checklist'!$H$31),'Section A - Field Checklist'!$H$31,"") | R46: Soil pH.
B47: Drainage feasibility (K-value) | E47: =IF(fa_SHALLOW="","DATA NEEDED",IF(fa_SHALLOW=0,"CLEAR",IF(fa_K="","DATA NEEDED",IF(fa_K<th_K,"WARNING","CLEAR")))) -> DATA NEEDED | G47: =IF(fa_SHALLOW="","Groundwater depth not measured.",IF(fa_SHALLOW=0,"No drainage requirement at the current groundwater depth.",IF(fa_K="","Drainage is indicated but K is missing: Hooghoudt drain spacing cannot be engineered.",IF(fa_K<th_K,"Drainage is needed (groundwater "&ROUND(fa_GWD,2)&" m) but subsoil K is only "&ROUND(fa_K,2)&" m/day (< "&ROUND(th_K,2)&"). Pipe drains will be uneconomical without prior deep ripping or structural conditioning.","Subsoil K = "&ROUND(fa_K,2)&" m/day is adequate for subsurface drain design (Hooghoudt).")))) -> Groundwater depth not measured. | P47: fa_SODIC | Q47: =IF(ISNUMBER(fa_SOD),IF(fa_SOD_src="ESP",IF(fa_ESP>=15,1,0),IF(fa_SOD>=th_SOD,1,0)),IF(AND(ISNUMBER(fa_pH),fa_pH>th_pHSOD),1,"")) | R47: 1 sodic, 0 not sodic, blank if undetermined. A measured CROSS/SAR (>= th_SOD) or ESP (>= 15%) always decides and pH is then ignored. Only when all three are missing does pH > th_pHSOD give 1, as a presumption (not an official criterion); formulas test AND(fa_SOD="",fa_SODIC=1) for that case.
P48: fa_ECw | Q48: =IF(ISNUMBER('Section A - Field Checklist'!$H$10),'Section A - Field Checklist'!$H$10,IF(ISNUMBER('Section A - Field Checklist'!$H$11),'Section A - Field Checklist'!$H$11/th_TDS,"")) | R48: Active ECw (dS/m): meter reading, else TDS / th_TDS.
B49: D | SELECTED MEASURES | P49: fa_ECw_src | Q49: =IF(ISNUMBER('Section A - Field Checklist'!$H$10),"Primary",IF(ISNUMBER('Section A - Field Checklist'!$H$11),"Fallback","")) | R49: Source of active ECw.
B50: =IF(fa_NSEL=0,"No measures selected yet. Open the 'Section C - Measure Selection' sheet and set 'Selected for Implementation?' to YES.",fa_NSEL&" measure(s) selected for implementation.") -> No measures selected yet. Open the 'Section C - Measure Selection' sheet and set 'Selected for Implementation?' to YES. | P50: fa_GWD | Q50: =IF(ISNUMBER('Section A - Field Checklist'!$H$12),'Section A - Field Checklist'!$H$12,"") | R50: Groundwater depth (m).
B51: Category | E51: Selected measure | H51: Targeted agronomic / hydrological mechanism | P51: fa_SHALLOW | Q51: =IF(ISNUMBER(fa_GWD),IF(fa_GWD<th_GW,1,0),"") | R51: 1 if groundwater is shallow.
B52: =IF(1>fa_NSEL,"",INDEX('Section C - Measure Selection'!$A$4:$A$24,MATCH(1,$Q$70:$Q$90,0))) | E52: =IF(1>fa_NSEL,"",INDEX('Section C - Measure Selection'!$B$4:$B$24,MATCH(1,$Q$70:$Q$90,0))) | H52: =IF(1>fa_NSEL,"",INDEX('Section C - Measure Selection'!$K$4:$K$24,MATCH(1,$Q$70:$Q$90,0))) | P52: fa_ECgw | Q52: =IF(ISNUMBER('Section A - Field Checklist'!$H$32),'Section A - Field Checklist'!$H$32,"") | R52: Groundwater salinity (dS/m).
B53: =IF(2>fa_NSEL,"",INDEX('Section C - Measure Selection'!$A$4:$A$24,MATCH(2,$Q$70:$Q$90,0))) | E53: =IF(2>fa_NSEL,"",INDEX('Section C - Measure Selection'!$B$4:$B$24,MATCH(2,$Q$70:$Q$90,0))) | H53: =IF(2>fa_NSEL,"",INDEX('Section C - Measure Selection'!$K$4:$K$24,MATCH(2,$Q$70:$Q$90,0))) | P53: fa_K | Q53: =IF(ISNUMBER('Section A - Field Checklist'!$H$15),'Section A - Field Checklist'!$H$15,IF(ISNUMBER('Section A - Field Checklist'!$H$16),'Section A - Field Checklist'!$H$16,"")) | R53: Active K (m/day): auger-hole, else PTF estimate.
B54: =IF(3>fa_NSEL,"",INDEX('Section C - Measure Selection'!$A$4:$A$24,MATCH(3,$Q$70:$Q$90,0))) | E54: =IF(3>fa_NSEL,"",INDEX('Section C - Measure Selection'!$B$4:$B$24,MATCH(3,$Q$70:$Q$90,0))) | H54: =IF(3>fa_NSEL,"",INDEX('Section C - Measure Selection'!$K$4:$K$24,MATCH(3,$Q$70:$Q$90,0))) | P54: fa_BD | Q54: =IF(ISNUMBER('Section A - Field Checklist'!$H$25),'Section A - Field Checklist'!$H$25,IF(ISNUMBER('Section A - Field Checklist'!$H$26),'Section A - Field Checklist'!$H$26,"")) | R54: Active bulk density (g/cm3).
B55: =IF(4>fa_NSEL,"",INDEX('Section C - Measure Selection'!$A$4:$A$24,MATCH(4,$Q$70:$Q$90,0))) | E55: =IF(4>fa_NSEL,"",INDEX('Section C - Measure Selection'!$B$4:$B$24,MATCH(4,$Q$70:$Q$90,0))) | H55: =IF(4>fa_NSEL,"",INDEX('Section C - Measure Selection'!$K$4:$K$24,MATCH(4,$Q$70:$Q$90,0))) | P55: fa_CEC | Q55: =IF(ISNUMBER('Section A - Field Checklist'!$H$23),'Section A - Field Checklist'!$H$23,IF(ISNUMBER('Section A - Field Checklist'!$H$24),'Section A - Field Checklist'!$H$24,"")) | R55: Active CEC (cmol/kg).
B56: =IF(5>fa_NSEL,"",INDEX('Section C - Measure Selection'!$A$4:$A$24,MATCH(5,$Q$70:$Q$90,0))) | E56: =IF(5>fa_NSEL,"",INDEX('Section C - Measure Selection'!$B$4:$B$24,MATCH(5,$Q$70:$Q$90,0))) | H56: =IF(5>fa_NSEL,"",INDEX('Section C - Measure Selection'!$K$4:$K$24,MATCH(5,$Q$70:$Q$90,0))) | P56: fa_LIME | Q56: =IF(ISNUMBER('Section A - Field Checklist'!$H$27),'Section A - Field Checklist'!$H$27,"") | R56: Native lime (% CaCO3), lab value.
B57: =IF(6>fa_NSEL,"",INDEX('Section C - Measure Selection'!$A$4:$A$24,MATCH(6,$Q$70:$Q$90,0))) | E57: =IF(6>fa_NSEL,"",INDEX('Section C - Measure Selection'!$B$4:$B$24,MATCH(6,$Q$70:$Q$90,0))) | H57: =IF(6>fa_NSEL,"",INDEX('Section C - Measure Selection'!$K$4:$K$24,MATCH(6,$Q$70:$Q$90,0))) | P57: fa_LIMEHIGH | Q57: =IF(ISNUMBER('Section A - Field Checklist'!$H$27),IF('Section A - Field Checklist'!$H$27>=th_LIME,1,0),IF(LEN(TRIM('Section A - Field Checklist'!$H$28&""))=0,"",IF(OR(ISNUMBER(SEARCH("strong",'Section A - Field Checklist'!$H$28)),ISNUMBER(SEARCH("violent",'Section A - Field Checklist'!$H$28)),ISNUMBER(SEARCH("high",'Section A - Field Checklist'!$H$28))),1,IF(OR(ISNUMBER(SEARCH("non",'Section A - Field Checklist'!$H$28)),ISNUMBER(SEARCH("nil",'Section A - Field Checklist'!$H$28)),ISNUMBER(SEARCH("absent",'Section A - Field Checklist'!$H$28)),LOWER(TRIM('Section A - Field Checklist'!$H$28&""))="no"),0,"")))) | R57: 1 lime-rich, 0 lime-poor, blank unknown. Lab % first; the HCl test counts as lime-rich only for 'strong'/'violent'/'high' and lime-poor only for 'none'/'nil'/'absent' (screening reading).
B58: =IF(7>fa_NSEL,"",INDEX('Section C - Measure Selection'!$A$4:$A$24,MATCH(7,$Q$70:$Q$90,0))) | E58: =IF(7>fa_NSEL,"",INDEX('Section C - Measure Selection'!$B$4:$B$24,MATCH(7,$Q$70:$Q$90,0))) | H58: =IF(7>fa_NSEL,"",INDEX('Section C - Measure Selection'!$K$4:$K$24,MATCH(7,$Q$70:$Q$90,0))) | P58: fa_RSC | Q58: =IF(ISNUMBER('Section A - Field Checklist'!$H$29),'Section A - Field Checklist'!$H$29,"") | R58: Residual sodium carbonate (meq/L).
B59: =IF(8>fa_NSEL,"",INDEX('Section C - Measure Selection'!$A$4:$A$24,MATCH(8,$Q$70:$Q$90,0))) | E59: =IF(8>fa_NSEL,"",INDEX('Section C - Measure Selection'!$B$4:$B$24,MATCH(8,$Q$70:$Q$90,0))) | H59: =IF(8>fa_NSEL,"",INDEX('Section C - Measure Selection'!$K$4:$K$24,MATCH(8,$Q$70:$Q$90,0))) | P59: fa_SOM | Q59: =IF(ISNUMBER('Section A - Field Checklist'!$H$35),'Section A - Field Checklist'!$H$35,IF(ISNUMBER('Section A - Field Checklist'!$H$36),'Section A - Field Checklist'!$H$36*th_TOC,"")) | R59: Active SOM (%): lab SOM, else TOC x th_TOC.
B60: =IF(9>fa_NSEL,"",INDEX('Section C - Measure Selection'!$A$4:$A$24,MATCH(9,$Q$70:$Q$90,0))) | E60: =IF(9>fa_NSEL,"",INDEX('Section C - Measure Selection'!$B$4:$B$24,MATCH(9,$Q$70:$Q$90,0))) | H60: =IF(9>fa_NSEL,"",INDEX('Section C - Measure Selection'!$K$4:$K$24,MATCH(9,$Q$70:$Q$90,0))) | P60: fa_ECt | Q60: =IF(ISNUMBER('Section A - Field Checklist'!$H$37),'Section A - Field Checklist'!$H$37,"") | R60: Crop salt tolerance threshold (dS/m).
B61: =IF(10>fa_NSEL,"",INDEX('Section C - Measure Selection'!$A$4:$A$24,MATCH(10,$Q$70:$Q$90,0))) | E61: =IF(10>fa_NSEL,"",INDEX('Section C - Measure Selection'!$B$4:$B$24,MATCH(10,$Q$70:$Q$90,0))) | H61: =IF(10>fa_NSEL,"",INDEX('Section C - Measure Selection'!$K$4:$K$24,MATCH(10,$Q$70:$Q$90,0))) | P61: fa_BUDGET | Q61: =IF(ISNUMBER('Section A - Field Checklist'!$H$39),IF('Section A - Field Checklist'!$H$39<100,"Low",IF('Section A - Field Checklist'!$H$39<=500,"Medium","High")),IF(ISNUMBER(SEARCH("low",'Section A - Field Checklist'!$H$39&"")),"Low",IF(ISNUMBER(SEARCH("high",'Section A - Field Checklist'!$H$39&"")),"High",IF(ISNUMBER(SEARCH("med",'Section A - Field Checklist'!$H$39&"")),"Medium","")))) | R61: Budget class: text, or EUR/ha mapped with Section B Table 21 (< 100 Low, 100-500 Medium, > 500 High).
B62: =IF(11>fa_NSEL,"",INDEX('Section C - Measure Selection'!$A$4:$A$24,MATCH(11,$Q$70:$Q$90,0))) | E62: =IF(11>fa_NSEL,"",INDEX('Section C - Measure Selection'!$B$4:$B$24,MATCH(11,$Q$70:$Q$90,0))) | H62: =IF(11>fa_NSEL,"",INDEX('Section C - Measure Selection'!$K$4:$K$24,MATCH(11,$Q$70:$Q$90,0))) | P62: fa_TOPO | Q62: =IF(ISNUMBER('Section A - Field Checklist'!$H$19),'Section A - Field Checklist'!$H$19,"") | R62: Micro-topography variance (cm).
B63: =IF(12>fa_NSEL,"",INDEX('Section C - Measure Selection'!$A$4:$A$24,MATCH(12,$Q$70:$Q$90,0))) | E63: =IF(12>fa_NSEL,"",INDEX('Section C - Measure Selection'!$B$4:$B$24,MATCH(12,$Q$70:$Q$90,0))) | H63: =IF(12>fa_NSEL,"",INDEX('Section C - Measure Selection'!$K$4:$K$24,MATCH(12,$Q$70:$Q$90,0))) | P63: fa_DEM | Q63: =IF(AND(LEN(TRIM('Section A - Field Checklist'!$H$20&""))>0,LOWER(TRIM('Section A - Field Checklist'!$H$20&""))<>"unknown"),1,0) -> 0 | R63: 1 if only a regional DEM value is available.
B64: =IF(13>fa_NSEL,"",INDEX('Section C - Measure Selection'!$A$4:$A$24,MATCH(13,$Q$70:$Q$90,0))) | E64: =IF(13>fa_NSEL,"",INDEX('Section C - Measure Selection'!$B$4:$B$24,MATCH(13,$Q$70:$Q$90,0))) | H64: =IF(13>fa_NSEL,"",INDEX('Section C - Measure Selection'!$K$4:$K$24,MATCH(13,$Q$70:$Q$90,0))) | P64: fa_INFIL | Q64: =IF(OR(fa_ECw="",fa_SOD=""),"",IF(fa_SOD<3,IF(fa_ECw>0.7,0,IF(fa_ECw>=0.2,1,2)),IF(fa_SOD<6,IF(fa_ECw>1.2,0,IF(fa_ECw>=0.3,1,2)),IF(fa_SOD<12,IF(fa_ECw>1.9,0,IF(fa_ECw>=0.5,1,2)),IF(fa_SOD<20,IF(fa_ECw>2.9,0,IF(fa_ECw>=1.3,1,2)),IF(fa_ECw>5,0,IF(fa_ECw>=2.9,1,2))))))) | R64: Infiltration restriction 0 none / 1 slight-moderate / 2 severe. FAO 29 Table 1 (Ayers & Westcot 1985), SAR bands 0-3/3-6/6-12/12-20/20-40; soil CROSS/SAR used as proxy for irrigation-water SAR. Thresholds listed in Section B Table 22.
B65: =IF(14>fa_NSEL,"",INDEX('Section C - Measure Selection'!$A$4:$A$24,MATCH(14,$Q$70:$Q$90,0))) | E65: =IF(14>fa_NSEL,"",INDEX('Section C - Measure Selection'!$B$4:$B$24,MATCH(14,$Q$70:$Q$90,0))) | H65: =IF(14>fa_NSEL,"",INDEX('Section C - Measure Selection'!$K$4:$K$24,MATCH(14,$Q$70:$Q$90,0))) | P65: fa_MASTER | Q65: =IF(fa_ECe="","Insufficient data",IF(fa_SOD="",IF(fa_SODIC=1,IF(fa_ECe>=th_SAL,"Probably Saline-Sodic (pH only, not confirmed)","Probably Sodic (pH only, not confirmed)"),IF(fa_ECe>=th_SAL,"Saline Soil, sodicity undetermined","Sodicity undetermined")),IF(fa_ECe>=th_SAL,IF(fa_SODIC=1,"Saline-Sodic Soil","Saline Soil ('White Alkali')"),IF(fa_SODIC=1,"Sodic Soil ('Black Alkali')","Normal Soil")))) -> Insufficient data | R65: USDA/FAO class, Richards (1954): ECe >= th_SAL and sodic flag. Without CROSS/SAR/ESP: 'Probably Sodic' if pH > th_pHSOD (indicative, not an official criterion), otherwise 'Sodicity undetermined'.
B66: =IF(15>fa_NSEL,"",INDEX('Section C - Measure Selection'!$A$4:$A$24,MATCH(15,$Q$70:$Q$90,0))) | E66: =IF(15>fa_NSEL,"",INDEX('Section C - Measure Selection'!$B$4:$B$24,MATCH(15,$Q$70:$Q$90,0))) | H66: =IF(15>fa_NSEL,"",INDEX('Section C - Measure Selection'!$K$4:$K$24,MATCH(15,$Q$70:$Q$90,0))) | P66: fa_ANYFB | Q66: =IF(OR(fa_ECe_src="Fallback",fa_SOD_src="SAR",fa_SOD_src="ESP"),1,0) -> 0 | R66: 1 if the classification relies on any fallback metric.
B67: =IF(16>fa_NSEL,"",INDEX('Section C - Measure Selection'!$A$4:$A$24,MATCH(16,$Q$70:$Q$90,0))) | E67: =IF(16>fa_NSEL,"",INDEX('Section C - Measure Selection'!$B$4:$B$24,MATCH(16,$Q$70:$Q$90,0))) | H67: =IF(16>fa_NSEL,"",INDEX('Section C - Measure Selection'!$K$4:$K$24,MATCH(16,$Q$70:$Q$90,0))) | P67: fa_NSEL | Q67: =IF(fa_RESET=1,0,COUNTIF('Section C - Measure Selection'!$P$4:$P$24,"Selected") + COUNTIF('Section C - Measure Selection'!$P$4:$P$24,TRUE())) -> 0 | R67: Number of measures marked YES.
B68: =IF(17>fa_NSEL,"",INDEX('Section C - Measure Selection'!$A$4:$A$24,MATCH(17,$Q$70:$Q$90,0))) | E68: =IF(17>fa_NSEL,"",INDEX('Section C - Measure Selection'!$B$4:$B$24,MATCH(17,$Q$70:$Q$90,0))) | H68: =IF(17>fa_NSEL,"",INDEX('Section C - Measure Selection'!$K$4:$K$24,MATCH(17,$Q$70:$Q$90,0))) | P68: fa_RESET | Q68: =IF($K$2="RESET (blank all results)",1,0) -> 0 | R68: 1 when the reset control in K2 is set to RESET: every processed input and every measure tick is ignored.
B69: =IF(18>fa_NSEL,"",INDEX('Section C - Measure Selection'!$A$4:$A$24,MATCH(18,$Q$70:$Q$90,0))) | E69: =IF(18>fa_NSEL,"",INDEX('Section C - Measure Selection'!$B$4:$B$24,MATCH(18,$Q$70:$Q$90,0))) | H69: =IF(18>fa_NSEL,"",INDEX('Section C - Measure Selection'!$K$4:$K$24,MATCH(18,$Q$70:$Q$90,0))) | P69: SELECTED-MEASURE INDEX (feeds Section D)
B70: =IF(19>fa_NSEL,"",INDEX('Section C - Measure Selection'!$A$4:$A$24,MATCH(19,$Q$70:$Q$90,0))) | E70: =IF(19>fa_NSEL,"",INDEX('Section C - Measure Selection'!$B$4:$B$24,MATCH(19,$Q$70:$Q$90,0))) | H70: =IF(19>fa_NSEL,"",INDEX('Section C - Measure Selection'!$K$4:$K$24,MATCH(19,$Q$70:$Q$90,0))) | P70: ='Section C - Measure Selection'!B4 -> Subsurface Pipe Drainage (SPD) | Q70: =IF(fa_RESET=1,"",IF(OR('Section C - Measure Selection'!P4="Selected",'Section C - Measure Selection'!P4=TRUE()), COUNTIF('Section C - Measure Selection'!$P$4:P4,"Selected") + COUNTIF('Section C - Measure Selection'!$P$4:P4,TRUE()), ""))
B71: =IF(20>fa_NSEL,"",INDEX('Section C - Measure Selection'!$A$4:$A$24,MATCH(20,$Q$70:$Q$90,0))) | E71: =IF(20>fa_NSEL,"",INDEX('Section C - Measure Selection'!$B$4:$B$24,MATCH(20,$Q$70:$Q$90,0))) | H71: =IF(20>fa_NSEL,"",INDEX('Section C - Measure Selection'!$K$4:$K$24,MATCH(20,$Q$70:$Q$90,0))) | P71: ='Section C - Measure Selection'!B5 -> Open Ditch Drainage | Q71: =IF(fa_RESET=1,"",IF(OR('Section C - Measure Selection'!P5="Selected",'Section C - Measure Selection'!P5=TRUE()), COUNTIF('Section C - Measure Selection'!$P$4:P5,"Selected") + COUNTIF('Section C - Measure Selection'!$P$4:P5,TRUE()), ""))
B72: =IF(21>fa_NSEL,"",INDEX('Section C - Measure Selection'!$A$4:$A$24,MATCH(21,$Q$70:$Q$90,0))) | E72: =IF(21>fa_NSEL,"",INDEX('Section C - Measure Selection'!$B$4:$B$24,MATCH(21,$Q$70:$Q$90,0))) | H72: =IF(21>fa_NSEL,"",INDEX('Section C - Measure Selection'!$K$4:$K$24,MATCH(21,$Q$70:$Q$90,0))) | P72: ='Section C - Measure Selection'!B6 -> Vertical Drainage / Tubewells | Q72: =IF(fa_RESET=1,"",IF(OR('Section C - Measure Selection'!P6="Selected",'Section C - Measure Selection'!P6=TRUE()), COUNTIF('Section C - Measure Selection'!$P$4:P6,"Selected") + COUNTIF('Section C - Measure Selection'!$P$4:P6,TRUE()), ""))
P73: ='Section C - Measure Selection'!B7 -> Canal Lining | Q73: =IF(fa_RESET=1,"",IF(OR('Section C - Measure Selection'!P7="Selected",'Section C - Measure Selection'!P7=TRUE()), COUNTIF('Section C - Measure Selection'!$P$4:P7,"Selected") + COUNTIF('Section C - Measure Selection'!$P$4:P7,TRUE()), ""))
P74: ='Section C - Measure Selection'!B8 -> Deep Ripping / DVRT (Deep Vertical Rotary Tillage) | Q74: =IF(fa_RESET=1,"",IF(OR('Section C - Measure Selection'!P8="Selected",'Section C - Measure Selection'!P8=TRUE()), COUNTIF('Section C - Measure Selection'!$P$4:P8,"Selected") + COUNTIF('Section C - Measure Selection'!$P$4:P8,TRUE()), ""))
P75: ='Section C - Measure Selection'!B9 -> Precision Land Leveling (Laser Grading) | Q75: =IF(fa_RESET=1,"",IF(OR('Section C - Measure Selection'!P9="Selected",'Section C - Measure Selection'!P9=TRUE()), COUNTIF('Section C - Measure Selection'!$P$4:P9,"Selected") + COUNTIF('Section C - Measure Selection'!$P$4:P9,TRUE()), ""))
P76: ='Section C - Measure Selection'!B10 -> Forced Leaching Regime | Q76: =IF(fa_RESET=1,"",IF(OR('Section C - Measure Selection'!P10="Selected",'Section C - Measure Selection'!P10=TRUE()), COUNTIF('Section C - Measure Selection'!$P$4:P10,"Selected") + COUNTIF('Section C - Measure Selection'!$P$4:P10,TRUE()), ""))
P77: ='Section C - Measure Selection'!B11 -> Gypsum Application (CaSO4·2H2O) | Q77: =IF(fa_RESET=1,"",IF(OR('Section C - Measure Selection'!P11="Selected",'Section C - Measure Selection'!P11=TRUE()), COUNTIF('Section C - Measure Selection'!$P$4:P11,"Selected") + COUNTIF('Section C - Measure Selection'!$P$4:P11,TRUE()), ""))
P78: ='Section C - Measure Selection'!B12 -> Soil Acidification (Elemental Sulfur / Acid Injection) | Q78: =IF(fa_RESET=1,"",IF(OR('Section C - Measure Selection'!P12="Selected",'Section C - Measure Selection'!P12=TRUE()), COUNTIF('Section C - Measure Selection'!$P$4:P12,"Selected") + COUNTIF('Section C - Measure Selection'!$P$4:P12,TRUE()), ""))
P79: ='Section C - Measure Selection'!B13 -> Organic Amendments (Compost, Manure, Biochar) | Q79: =IF(fa_RESET=1,"",IF(OR('Section C - Measure Selection'!P13="Selected",'Section C - Measure Selection'!P13=TRUE()), COUNTIF('Section C - Measure Selection'!$P$4:P13,"Selected") + COUNTIF('Section C - Measure Selection'!$P$4:P13,TRUE()), ""))
P80: ='Section C - Measure Selection'!B14 -> Irrigation Water Acidification | Q80: =IF(fa_RESET=1,"",IF(OR('Section C - Measure Selection'!P14="Selected",'Section C - Measure Selection'!P14=TRUE()), COUNTIF('Section C - Measure Selection'!$P$4:P14,"Selected") + COUNTIF('Section C - Measure Selection'!$P$4:P14,TRUE()), ""))
P81: ='Section C - Measure Selection'!B15 -> Mulched Drip Irrigation (MDI) | Q81: =IF(fa_RESET=1,"",IF(OR('Section C - Measure Selection'!P15="Selected",'Section C - Measure Selection'!P15=TRUE()), COUNTIF('Section C - Measure Selection'!$P$4:P15,"Selected") + COUNTIF('Section C - Measure Selection'!$P$4:P15,TRUE()), ""))
P82: ='Section C - Measure Selection'!B16 -> Biosaline Agriculture & Salt-Tolerant Crops | Q82: =IF(fa_RESET=1,"",IF(OR('Section C - Measure Selection'!P16="Selected",'Section C - Measure Selection'!P16=TRUE()), COUNTIF('Section C - Measure Selection'!$P$4:P16,"Selected") + COUNTIF('Section C - Measure Selection'!$P$4:P16,TRUE()), ""))
P83: ='Section C - Measure Selection'!B17 -> Biodrainage (Deep-Rooted Trees) | Q83: =IF(fa_RESET=1,"",IF(OR('Section C - Measure Selection'!P17="Selected",'Section C - Measure Selection'!P17=TRUE()), COUNTIF('Section C - Measure Selection'!$P$4:P17,"Selected") + COUNTIF('Section C - Measure Selection'!$P$4:P17,TRUE()), ""))
P84: ='Section C - Measure Selection'!B18 -> Microbial Bio-Inoculation (PGPR & Mycorrhizae) | Q84: =IF(fa_RESET=1,"",IF(OR('Section C - Measure Selection'!P18="Selected",'Section C - Measure Selection'!P18=TRUE()), COUNTIF('Section C - Measure Selection'!$P$4:P18,"Selected") + COUNTIF('Section C - Measure Selection'!$P$4:P18,TRUE()), ""))
... P90: ='Section C - Measure Selection'!B24 -> Aquifer Storage and Recovery (ASR) | Q90: =IF(fa_RESET=1,"",IF(OR('Section C - Measure Selection'!P24="Selected",'Section C - Measure Selection'!P24=TRUE()), COUNTIF('Section C - Measure Selection'!$P$4:P24,"Selected") + COUNTIF('Section C - Measure Selection'!$P$4:P24,TRUE()), ""))

Sheet Section A - Field Checklist
C1: FIELD ASSESSMENT & DIAGNOSTIC PROTOCOL: 0-METING BASELINE
C3: Priority | D3: Input Category | E3: Input (drop-down) | F3: Input (manual) | G3: Field Parameter | H3: Final Processed Value | I3: Unit | J3: Field / Lab Measurement Method | K3: Diagnostic & Project Impact | L3: Scientific Source & Grounding
C4: Priority 1: Baseline Screening & Assessing Risks
C5: Priority 1: Critical (Must-Have) | D5: Soil Salinity | G5: Soil ECe (Soil Salinity) [Primary] | H5: =IF(fa_RESET=1,"",IF(E5="0.0 – 2.0 dS/m",1,IF(E5="2.0 – 4.0 dS/m",3,IF(E5="4.0 – 8.0 dS/m",6,IF(E5="8.0 – 16.0 dS/m",12,IF(E5="> 16.0 dS/m",18,IF(E5="Manual",IF(F5="","",F5),IF(F5="","",F5)))))))) | I5: dS/m | J5: Conductivity test of saturated soil paste extract at 25°C | K5: Measures total dissolved salts and osmotic stress. Foundation for calculating leaching fractions. | L5: Richards (1954); Van Hoorn & Van Alphen (1994)
G6: Soil EC1:5 / EM38 [Fallback] | H6: =IF(fa_RESET=1,"",IF(E6="< 0.4 dS/m",0.2,IF(E6="0.4 – 0.8 dS/m",0.6,IF(E6="0.8 – 1.6 dS/m",1.2,IF(E6="> 1.6 dS/m",2,IF(E6="Manual",IF(F6="","",F6),IF(F6="","",F6))))))) | I6: dS/m | J6: Conductivity test of 1:5 soil-water extract or field EM sensor scan | K6: Quick screening fallback. Diluted extracts alter chemical equilibrium if lime or gypsum is present. | L6: Dehaan & Taylor (2002); Liu et al. (2025)
C7: Priority 1: Critical (Must-Have) | D7: Sodicity | G7: CROSS (Cation Ratio) [Primary Gold Std] | H7: =IF(fa_RESET=1,"",IF(E7="< 13.0 (mmol/L)^0.5",10,IF(E7="13.0 – 20.0 (mmol/L)^0.5",16.5,IF(E7="> 20.0 (mmol/L)^0.5",25,IF(E7="Manual",IF(F7="","",F7),IF(F7="","",F7)))))) | I7: (mmol/L)^0.5 | J7: Lab ICP/AAS test of Na+, K+, Ca2+, Mg2+ in saturation extract | K7: Gold standard for clay dispersion. Accounts for K+ dispersion and distinct Ca2+ vs Mg2+ flocculating power. | L7: Rengasamy & Marchuk (2011)
G8: SAR (Sodium Adsorption Ratio) [Secondary] | H8: =IF(fa_RESET=1,"",IF(E8="< 13.0 (mmol/L)^0.5",10,IF(E8="≥ 13.0 (mmol/L)^0.5",15,IF(E8="Manual",IF(F8="","",F8),IF(F8="","",F8))))) | I8: (mmol/L)^0.5 | J8: Lab measurement of soluble Na+, Ca2+, and Mg2+ in saturation extract | K8: Standard benchmark for sodic hazard. Predicts aggregate breakdown and surface crusting. | L8: Richards (1954); Van Hoorn & Van Alphen (1994)
G9: ESP (Exchangeable Sodium %) [Fallback] | H9: =IF(fa_RESET=1,"",IF(E9="< 15%",10,IF(E9="15% – 30%",22.5,IF(E9="> 30%",35,IF(E9="Manual",IF(F9="","",F9),IF(F9="","",F9)))))) | I9: % of CEC | J9: Lab measurement of exchangeable Na+ relative to Cation Exchange Capacity (CEC) | K9: Measures Na+ adsorbed on clay complex. Usually calculated from SAR because CEC testing is slow. | L9: Richards (1954); Van Hoorn & Van Alphen (1994)
C10: Priority 1: Critical (Must-Have) | D10: Irrigation Water Salinity | G10: Irrigation Water Salinity (ECw) [Primary] | H10: =IF(fa_RESET=1,"",IF(E10="< 0.7 dS/m",0.5,IF(E10="0.7 – 3.0 dS/m",1.85,IF(E10="> 3.0 dS/m",4,IF(E10="Manual",IF(F10="","",F10),IF(F10="","",F10)))))) | I10: dS/m | J10: Direct field conductivity meter measurement of irrigation water source | K10: Determines external salt loading rate and required leaching fraction (LF) to maintain rootzone salt balance. | L10: Ayers & Westcot (1985); Doneen (1954)
G11: Irrigation Water Salinity (TDS) [Fallback] | H11: =IF(fa_RESET=1,"",IF(E11="< 450 mg/L (ppm)",250,IF(E11="450 – 2000 mg/L",1225,IF(E11="> 2000 mg/L",2500,IF(E11="Manual",IF(F11="","",F11),IF(F11="","",F11)))))) | I11: mg/L (ppm) | J11: Gravimetric drying or estimated via TDS ≈ 640 * ECw | K11: Fallback when conductivity meter is unavailable; measures total solute mass rather than electrical charge. | L11: Doneen (1954); Karimzadeh et al. (2024)
C12: Priority 1: Critical (Must-Have) | D12: Groundwater Depth | G12: Groundwater Depth (Water Table) [Primary] | H12: =IF(fa_RESET=1,"",IF(E12="> 2.0 m",2.5,IF(E12="1.5 – 2.0 m",1.75,IF(E12="< 1.5 m",1,IF(E12="Manual",IF(F12="","",F12),IF(F12="","",F12)))))) | I12: Meters (m) | J12: Regular monitoring via network of grid-allocated piezometers or observation wells | K12: Water table < 1.5 - 2.0 m triggers capillary rise of saline groundwater, causing rapid surface salinization. | L12: Ritzema (1994); Bhutta & Smedema (2007)
C14: Priority 2: System Diagnosis & Hydraulic Feasibility
C15: Priority 2: Essential (Design & Engineering) | D15: Permeability | G15: Hydraulic Conductivity (K-value) [Primary] | H15: =IF(fa_RESET=1,"",IF(E15="> 2.0 m/day",2.5,IF(E15="0.5 – 2.0 m/day",1.25,IF(E15="0.1 – 0.5 m/day",0.3,IF(E15="< 0.1 m/day",0.05,IF(E15="Manual",IF(F15="","",F15),IF(F15="","",F15))))))) | I15: m/day | J15: In-situ field measurements using auger-hole method below water table or ring infiltrometer | K15: Single most critical parameter for subsurface drainage design. Determines drain pipe spacing (L). | L15: Ritzema (1994); Van Hoorn & Van Alphen (1994)
G16: Hydraulic Conductivity (PTF) [Fallback] | H16: =IF(fa_RESET=1,"",IF(E16="> 2.0 m/day",2.5,IF(E16="0.5 – 2.0 m/day",1.25,IF(E16="0.1 – 0.5 m/day",0.3,IF(E16="< 0.1 m/day",0.05,IF(E16="Manual",IF(F16="","",F16),IF(F16="","",F16))))))) | I16: m/day (est.) | J16: Empirical Pedotransfer Function estimation based on sand, silt, clay, and bulk density | K16: Desktop fallback when field water flow testing is unfeasible. Less accurate in structured clay soils. | L16: Liu et al. (2025)
C17: Priority 2: Essential (Design & Engineering) | D17: Texture & Horizonation | G17: Soil Texture & Layering [Primary] | H17: =IF(fa_RESET=1,"",IF(E17="Coarse (Sand / Loamy Sand)","Sand",IF(E17="Medium (Loam / Silt Loam / Sandy Loam)","Loam",IF(E17="Fine (Clay / Silty Clay / Clay Loam)","Clay",IF(E17="Stratified (Clay pans / Plow pans)","Stratified",IF(E17="Manual",IF(F17="","",F17),IF(F17="","",F17))))))) | I17: USDA Class | J17: Sieve and hydrometer/pipette grain-size distribution analysis in laboratory | K17: Governs water retention, capillary rise height, and leaching efficiency. Clay seals block vertical flow. | L17: Richards (1954); Liu et al. (2025)
G18: Soil Texture (Hand Test) [Fallback] | H18: =IF(fa_RESET=1,"",IF(E18="Coarse (Sand / Loamy Sand)","Sand",IF(E18="Medium (Loam / Silt Loam / Sandy Loam)","Loam",IF(E18="Fine (Clay / Silty Clay / Clay Loam)","Clay",IF(E18="Stratified (Clay pans / Plow pans)","Stratified",IF(E18="Manual",IF(F18="","",F18),IF(F18="","",F18))))))) | I18: Textural Class | J18: Manual ribbon kneading test and visual auger logging in the field | K18: Quick field screening to classify soil texture and detect restrictive clay pans or hardpans during augering. | L18: Van Hoorn & Van Alphen (1994)
C19: Priority 2: Essential (Design & Engineering) | D19: Topography & Relief | G19: Micro-topography & Slope [Primary] | H19: =IF(fa_RESET=1,"",IF(E19="Flat (< 0.1% slope) with depressions",0.05,IF(E19="Gentle Slope (0.1% – 1.0%)",0.5,IF(E19="Moderate to Steep (> 1.0%)",2,IF(E19="Manual",IF(F19="","",F19),IF(F19="","",F19)))))) | I19: cm elevation / % | J19: Field survey using RTK-GPS leveling, optical leveling instruments, or drone LiDAR | K19: Uneven land causes water accumulation in depressions (anoxia) and salt scalds on high spots. | L19: Savva & Frenken (2002); Singh (2019)
G20: Regional DEM (Satellite) [Fallback] | H20: =IF(fa_RESET=1,"",IF(F20="","",F20)) | I20: m (grid) | J20: GIS satellite digital elevation model (e.g. SRTM / DEM) extraction | K20: Macro-scale elevation fallback. Lacks fine micro-relief resolution needed for precision land leveling. | L20: Yu et al. (2010); Serati et al. (2025)
C22: Priority 3: Chemical Reclamation & Sodicity Quantification
C23: Priority 3: Conditional (Sodic Reclamation) | D23: Cation Exchange & Buffer | G23: CEC (Cation Exchange Capacity) [Primary] | H23: =IF(fa_RESET=1,"",IF(E23="< 10 meq/100g (cmol/kg)",5,IF(E23="10 – 20 meq/100g (cmol/kg)",15,IF(E23="> 20 meq/100g (cmol/kg)",25,IF(E23="Manual",IF(F23="","",F23),IF(F23="","",F23)))))) | I23: meq/100g or cmol/kg | J23: Ammonium acetate extraction at pH 7.0 or sodium acetate exchange in certified laboratory | K23: Conditional: MUST-HAVE if soil is sodic (SAR ≥ 13, or pH > 8.5 without SAR). Essential multiplier to calculate Gypsum Requirement. | L23: Richards (1954); Van Hoorn & Van Alphen (1994)
G24: CEC (Regression Estimate) [Fallback] | H24: =IF(fa_RESET=1,"",IF(E24="< 10 meq/100g (cmol/kg)",5,IF(E24="10 – 20 meq/100g (cmol/kg)",15,IF(E24="> 20 meq/100g (cmol/kg)",25,IF(E24="Manual",IF(F24="","",F24),IF(F24="","",F24)))))) | I24: cmol/kg (est.) | J24: Empirical regression formula: CEC ≈ (0.5 * %Clay) + (2.0 * %SOM) | K24: Inexpensive estimation fallback when laboratory CEC distillation testing is unavailable. | L24: Van Hoorn & Van Alphen (1994)
C25: Priority 3: Conditional (Sodic Reclamation) | D25: Physical Density | G25: Soil Bulk Density (ρb) [Primary] | H25: =IF(fa_RESET=1,"",IF(E25="< 1.4 g/cm³",1.2,IF(E25="1.4 – 1.6 g/cm³",1.5,IF(E25="> 1.6 g/cm³",1.7,IF(E25="Manual",IF(F25="","",F25),IF(F25="","",F25)))))) | I25: g/cm^3 | J25: Undisturbed soil core ring sampling of known volume, dried at 105°C and weighed | K25: Conditional: MUST-HAVE if sodic. Required to convert mass-based gypsum requirement to volume-based field tons/ha. | L25: Van Hoorn & Van Alphen (1994); Liu et al. (2025)
G26: Soil Bulk Density (Table Value) [Fallback] | H26: =IF(fa_RESET=1,"",IF(E26="< 1.4 g/cm³",1.2,IF(E26="1.4 – 1.6 g/cm³",1.5,IF(E26="> 1.6 g/cm³",1.7,IF(E26="Manual",IF(F26="","",F26),IF(F26="","",F26)))))) | I26: g/cm^3 (table) | J26: Standard soil physics table value based on soil texture class | K26: Practical default fallback for gypsum dosing calculations when physical core sampling cannot be performed. | L26: Liu et al. (2025)
C27: Priority 3: Conditional (Sodic Reclamation) | D27: Native Lime Reserve | G27: Native Lime (CaCO3 Equivalent) [Primary] | H27: =IF(fa_RESET=1,"",IF(E27="< 1.0%",0.5,IF(E27="1.0% – 5.0%",3,IF(E27="> 5.0%",6,IF(E27="Manual",IF(F27="","",F27),IF(F27="","",F27)))))) | I27: % CaCO3 | J27: Acid neutralization / gas calcimeter (Scheibler) method in laboratory on soil samples | K27: Conditional: MUST-HAVE if sodic. High native lime allows cheap reclamation using elemental sulfur/acid instead of gypsum. | L27: Van Hoorn & Van Alphen (1994); Liu et al. (2026)
G28: Native Lime (Field HCl Test) [Fallback] | H28: =IF(fa_RESET=1,"",IF(F28="","",F28)) | I28: Qualitative Rating | J28: Field test applying 10% hydrochloric acid drops to soil sample and observing effervescence | K28: Quick qualitative field test to confirm whether soil contains lime before selecting chemical amendments. | L28: Van Hoorn & Van Alphen (1994)
C29: Priority 3: Conditional (Sodic Reclamation) | D29: Carbonate Risk | G29: Residual Sodium Carbonate (RSC) [Primary] | H29: =IF(fa_RESET=1,"",IF(E29="< 1.25 meq/L",1,IF(E29="1.25 – 2.50 meq/L",1.8,IF(E29="> 2.50 meq/L",3,IF(E29="Manual",IF(F29="","",F29),IF(F29="","",F29)))))) | I29: meq/L | J29: Titration of HCO3- and CO32- minus (Ca2+ + Mg2+) in irrigation water | K29: Assesses hazard of carbonate precipitation; RSC > 2.5 meq/L causes Ca/Mg precipitation, elevating effective SAR. | L29: Eaton (1950); Ayers & Westcot (1985)
G30: Adjusted SAR (SARadj) [Fallback] | H30: =IF(fa_RESET=1,"",IF(F30="","",F30)) | I30: (mmol/L)^0.5 | J30: Computational adjustment of SAR accounting for potential bicarbonate precipitation | K30: Integrates carbonate precipitation directly into the irrigation water rating without separate RSC thresholding. | L30: Ayers & Westcot (1985); Lesch & Suarez (2009)
C31: Priority 1: Critical (Must-Have) | D31: Soil pH | G31: Soil pH [Primary] | H31: =IF(fa_RESET=1,"",IF(E31="< 7.5",7,IF(E31="7.5 – 8.5",8,IF(E31="> 8.5",9,IF(E31="Manual",IF(F31="","",F31),IF(F31="","",F31)))))) | I31: pH scale (1-14) | J31: Lab 1:5 soil:water extract using calibrated digital pH electrode or field pen | K31: Direct indicator of sodic dispersion risk if pH > 8.5. Dictates whether elemental sulfur/acid can dissolve native CaCO3. | L31: Richards (1954)
C32: Priority 1: Critical (Must-Have) | D32: Groundwater Salinity | G32: Groundwater Salinity (ECgw) [Primary] | H32: =IF(fa_RESET=1,"",IF(E32="< 1.5 dS/m",1,IF(E32="1.5 – 5.0 dS/m",3,IF(E32="> 5.0 dS/m",6,IF(E32="Manual",IF(F32="","",F32),IF(F32="","",F32)))))) | I32: dS/m | J32: Direct conductivity measurement of groundwater sampled from piezometer network | K32: Determines the concentration of salts in shallow groundwater that will rise into the root zone upon evaporation. | L32: Bhutta & Smedema (2007); Liu et al. (2025)
C34: Priority 4: Agronomic Adaptation & Economic Feasibility
C35: Priority 4: Agronomic & Management | D35: Organic Carbon | G35: Soil Organic Matter (SOM) [Primary] | H35: =IF(fa_RESET=1,"",IF(E35="< 1.0%",0.5,IF(E35="1.0% – 2.0%",1.5,IF(E35="> 2.0%",2.5,IF(E35="Manual",IF(F35="","",F35),IF(F35="","",F35)))))) | I35: % | J35: Walkley-Black chromic acid wet oxidation or Loss on Ignition (LOI 550°C) in laboratory | K35: Promotes structural aggregation and biological activity. Stabilizes 'card-house' clay structure against sodic dispersion. | L35: Abrol et al. (1988); Ma et al. (2025)
G36: Total Organic Carbon (TOC) [Fallback] | H36: =IF(fa_RESET=1,"",IF(F36="","",F36)) | I36: % TOC | J36: High-temperature dry combustion elemental analyzer (SOM ≈ 1.724 * TOC) | K36: Analytical fallback measuring elemental organic carbon; requires conversion factor to estimate SOM. | L36: Ma et al. (2025)
C37: Priority 4: Agronomic & Management | D37: Crop Tolerance | G37: Crop/Cultivar Salt Tolerance (ECt) [Primary] | H37: =IF(fa_RESET=1,"",IF(E37="< 1.5 dS/m",1,IF(E37="1.5 – 3.0 dS/m",2.25,IF(E37="3.0 – 6.0 dS/m",4.5,IF(E37="6.0 – 10.0 dS/m",8,IF(E37="> 10.0 dS/m",12,IF(E37="Manual",IF(F37="","",F37),IF(F37="","",F37)))))))) | I37: dS/m | J37: Lookup from standard agronomic reference databases (Maas-Hoffman 1977 or FAO guidelines) | K37: Determines threshold soil salinity (ECt) before yield decline begins. Vital to calculate minimum leaching requirement. | L37: Maas & Hoffman (1977); Singh (2019)
G38: Local Yield / Crop Group [Fallback] | H38: =IF(fa_RESET=1,"",IF(F38="","",F38)) | I38: Relative Yield % | J38: Local farmer yield history and empirical crop group comparison | K38: Practical fallback when cultivar-specific tolerance curves are unavailable in published literature. | L38: Karimzadeh et al. (2024)
C39: Priority 4: Agronomic & Management | D39: Capital & Budget | G39: Socio-Economic & Available Budget [Primary] | H39: =IF(fa_RESET=1,"",IF(F39="","",F39)) | I39: Qualitative / €/ha | J39: Farmers' household surveys, structured interviews, and agricultural record audits | K39: Dictates financial feasibility of high-capital engineering (subsurface pipe drainage) vs low-capital agronomic shifts. | L39: Janmaat (2005); Bhutta & Smedema (2007)

Sheet Section B - Classification 1
A1: SECTION B: DIAGNOSTIC CRITERIA & SOIL CLASSIFICATION (THE BRIDGE)
A2: Comprehensive Classification Framework, Thresholds, Action Protocols & Grounding Citations Per Row
A4: TABLE 1: MASTER SOIL CLASSIFICATION FRAMEWORK (Richards 1954 / USSL / FAO)
A5: Soil Classification | B5: ECe Threshold (dS/m) | C5: SAR / ESP Boundary | D5: Typical Soil pH (Descriptive) | E5: Physical & Structural Status | F5: Agronomic / Physical Hazard | G5: Immediate Action / Protocol & Scientific Source
A6: Normal / Calcareous Soil | B6: < 4.0 dS/m | C6: SAR < 13 ESP < 15% | D6: < 8.3 (Neutral to slightly alkaline) | E6: Stable 'card-house' aggregate structure; Ca2+ and Mg2+ dominate the exchange complex. | F6: None; optimal water infiltration, soil tilth, and plant water uptake are fully maintained. | G6: No chemical reclamation required. Monitor groundwater depth to prevent future rising. [Richards, 1954]
A7: Saline Soil ('White Alkali') | B7: ≥ 4.0 dS/m | C7: SAR < 13 ESP < 15% | D7: < 8.5 (Buffered by neutral salts) | E7: Structure remains flocculated and pore spaces intact due to high electrolyte concentration. | F7: Severe Osmotic Stress; plants experience 'physiological drought'. Visible salt scalds on drying. | G7: Washing/leaching with high-quality water is safe. Install subsurface drainage (SPD) to discharge flushed salts. [Richards, 1954; Van Hoorn & Van Alphen, 1994]
A8: Sodic Soil ('Black Alkali') | B8: < 4.0 dS/m | C8: SAR ≥ 13 ESP ≥ 15% | D8: > 8.5 (Can reach 10.0 due to Na2CO3) | E8: Severe clay dispersion, swelling, aggregate collapse, soil pore clogging, surface crusting. | F8: Total structural collapse; formation of an impenetrable physical crust that blocks water and seedling emergence. | G8: DO NOT FLUSH WITH FRESH WATER! Incorporate Gypsum (CaSO4) first to displace Na+ with Ca2+, then leach and drain. [Richards, 1954; Abrol et al., 1988]
A9: Saline-Sodic Soil | B9: ≥ 4.0 dS/m | C9: SAR ≥ 13 ESP ≥ 15% | D9: Variable (< 8.5, but > 8.5 if Na2CO3 present) | E9: Temporarily stable due to high salinity, but structurally highly unstable to fresh water. | F9: The 'Leaching Trap'; flushing salts without calcium drops salinity first, causing DDL expansion and immediate dispersion. | G9: Apply Gypsum (or sulfur/acid if calcareous) before or during leaching to maintain structural integrity as salinity drops. [Richards, 1954; Van Hoorn & Van Alphen, 1994]
A11: TABLE 2: SOIL REACTION (pH) — DESCRIPTIVE ALKALINITY INDICATOR
A12: Parameter Name | B12: Value / Range | C12: Classification / Class | D12: Field / Lab Measurement Method | E12: Agronomic & Soil Physical Impact | F12: Immediate Action / Protocol | G12: Scientific Source & Grounding
A13: Soil pH | B13: < 7.5 | C13: Acidic to Neutral | D13: Lab 1:5 soil-water extract with digital electrode | E13: Optimal chemical and nutrient balance; no salinity/sodicity-related pH stress. | F13: Standard crop fertilization and field management; no pH amendments needed. | G13: Doneen (1954)
A14: Soil pH | B14: 7.5 – 8.5 | C14: Slightly Alkaline (Calcareous) | D14: Lab 1:5 soil-water extract or field pH pen | E14: Typically buffered by calcium carbonate (CaCO3). Soluble micronutrients may become less available. | F14: If sodic (SAR ≥ 13), apply acidifying agents (elemental sulfur/acid) to dissolve calcareous lime and release Ca2+. | G14: Richards (1954); Ma et al. (2025)
A15: Soil pH | B15: > 8.5 | C15: Strongly Alkaline (Alkali/Sodic) | D15: Lab 1:5 soil-water extract or phenolphthalein test | E15: Indicates toxic sodium carbonates (Na2CO3); severe clay dispersion, aggregate collapse, and soil toxicity. | F15: Dose agricultural gypsum (CaSO_4), or use sulfur/acid ONLY if native lime (CaCO3 > 1%) is confirmed | G15: Richards (1954); Abrol et al. (1988)
A16: ASSUMPTIONS & CONSIDERATIONS FOR SOIL pH: Assumption: A soil pH above 8.5 indicates sodium carbonate (Na2CO3) and a probable sodic soil. The model uses this only as a presumption when CROSS, SAR or ESP is missing; it is not an official classification criterion. Critical Consideration: Soil pH is a descriptive qualifier; destructive clay dispersion can still occur at lower pH values if soil electrolyte concentration drops.
A18: TABLE 3: SOIL SALINITY — SOIL ECe (SATURATED PASTE EXTRACT)
A19: Parameter Name | B19: Value / Range | C19: Classification / Class | D19: Field / Lab Measurement Method | E19: Agronomic & Soil Physical Impact | F19: Immediate Action / Protocol | G19: Scientific Source & Grounding
A20: Soil ECe | B20: 0.0 – 2.0 dS/m | C20: Non-Saline | D20: Saturated soil paste extract conductivity at 25°C | E20: Salinity effects are negligible; safe for all common agricultural crops. | F20: Standard irrigation practices; maintain good on-farm water management. | G20: Richards (1954)
A21: Soil ECe | B21: 2.0 – 4.0 dS/m | C21: Slightly Saline | D21: Saturated soil paste extract conductivity at 25°C | E21: Yields of highly salt-sensitive crops (e.g. onions, carrots, beans) may be restricted. | F21: Incorporate a light Leaching Fraction (LF) into irrigation scheduling to prevent rootzone salt buildup. | G21: Richards (1954); Van Hoorn & Van Alphen (1994)
A22: Soil ECe | B22: 4.0 – 8.0 dS/m | C22: Moderately Saline | D22: Saturated soil paste extract conductivity at 25°C | E22: Yields of many common agricultural crops are restricted due to osmotic stress (physiological drought). | F22: Apply active leaching (excess water application) and regular soil ECe monitoring. Select moderately tolerant crop cultivars. | G22: Richards (1954); Van Hoorn & Van Alphen (1994)
A23: Soil ECe | B23: 8.0 – 16.0 dS/m | C23: Strongly Saline | D23: Saturated soil paste extract conductivity at 25°C | E23: Severe osmotic stress; only salt-tolerant crops (e.g. barley, cotton, sugarbeet) can yield satisfactorily. | F23: Implement active, intensive leaching and subsurface drainage. Shift to salt-tolerant crop cultivars. | G23: Richards (1954); Maas & Hoffman (1977)
A24: Soil ECe | B24: > 16.0 dS/m | C24: Very Strongly Saline | D24: Saturated soil paste extract conductivity at 25°C | E24: Extreme osmotic stress; virtually all regular crop species suffer complete yield collapse or death. | F24: Apply heavy freshwater flushing or shift entirely to halophytic forage/crops (e.g., Atriplex, Salicornia). | G24: Richards (1954); Van Orshoven et al. (2012)
A25: ASSUMPTIONS & CONSIDERATIONS FOR SOIL ECe: Assumption: Assumes ECe accurately represents rootzone osmotic stress under field moisture conditions. Critical Consideration: ECe measures non-specific osmotic potential and does not capture specific ion toxicities (chloride Cl-, sodium Na+, boron B). Sensitive woody perennials, fruit trees, and legumes frequently suffer severe foliar necrosis and metabolic collapse at low ECe levels due to ion-specific accumulation. Additionally, actual rootzone soil solution salinity under field capacity is typically 2 to 4 times higher than lab-measured ECe due to dilution in the saturated paste.
A27: TABLE 4: SOIL SALINITY — DILUTE EXTRACT (EC1:5 FALLBACK)
A28: Parameter Name | B28: Value / Range | C28: Classification / Class | D28: Field / Lab Measurement Method | E28: Agronomic & Soil Physical Impact | F28: Immediate Action / Protocol | G28: Scientific Source & Grounding
A29: Soil EC1:5 | B29: < 0.4 dS/m | C29: Low Salinity | D29: 1:5 soil:water ratio extract conductivity test | E29: Minimal osmotic stress; safe for general agricultural production. | F29: Standard water management; monitor field salinity seasonally. | G29: Dehaan & Taylor (2002)
A30: Soil EC1:5 | B30: 0.4 – 0.8 dS/m | C30: Medium Salinity | D30: 1:5 soil:water ratio extract conductivity test | E30: Yields of sensitive crops begin to decline; mild osmotic stress. | F30: Increase irrigation depth slightly to initiate salt flushing below tillage layer. | G30: Dehaan & Taylor (2002); Liu et al. (2025)
A31: Soil EC1:5 | B31: 0.8 – 1.6 dS/m | C31: High Salinity | D31: 1:5 soil:water ratio extract conductivity test | E31: Yields of moderately tolerant crops are restricted; noticeable osmotic drought. | F31: Apply leaching and convert EC1:5 to equivalent saturated paste ECe using texture-specific multiplier: ECe approx ftext times EC1:5 (where ftext approx 6.0 for coarse sand, 8.5 for loam/silt, 12.0 for clay loam, and 16.0 for heavy clay). Verify with laboratory saturated paste extract before engineering drainage dimensions. | G31: Dehaan & Taylor (2002); Liu et al. (2025)
A32: Soil EC1:5 | B32: > 1.6 dS/m | C32: Excessively High Salinity | D32: 1:5 soil:water ratio extract conductivity test | E32: Severe rootzone salinization; major crop damage or failure. | F32: Mandatory intensive flushing and drainage installation; switch to salt-tolerant crops. | G32: Dehaan & Taylor (2002); Shirokova et al. (2000)
A33: ASSUMPTIONS & CONSIDERATIONS FOR EC1:5: Assumption: Assumes a linear conversion factor between 1:5 dilute extract conductivity and saturated paste ECe. Critical Consideration: he conversion factor (f = ECe / EC1:5) depends heavily on soil saturation percentage (SP), varying from ~6 in sands to >15 in heavy clays. Furthermore, in soils containing gypsum or native calcium carbonate, dilute 1:5 extraction overestimates true field salinity due to mineral dissolution at higher dilution ratios.
A35: TABLE 5: SODICITY RISK — CROSS (CATION RATIO OF STRUCTURAL STABILITY)
A36: Parameter Name | B36: Value / Range | C36: Classification / Class | D36: Field / Lab Measurement Method | E36: Agronomic & Soil Physical Impact | F36: Immediate Action / Protocol | G36: Scientific Source & Grounding
A37: CROSS | B37: < 13.0 (mmol/L)^0.5 | C37: Non-Sodic | D37: Lab ICP/AAS test of Na+, K+, Ca2+, Mg2+ in saturation extract | E37: Clay platelets remain stable and flocculated; normal soil structure, pore space, and water infiltration. | F37: No chemical amelioration required; focus strictly on physical and hydrological water management. | G37: FAO & ICBA (2023) / WASAG Farmers' Guidelines (Tabel 6 & 7); gebaseerd op Rengasamy & Marchuk (2011)
A38: CROSS | B38: 13.0 – 20.0 (mmol/L)^0.5 | C38: Moderately Sodic | D38: Lab ICP/AAS test of Na+, K+, Ca2+, Mg2+ in saturation extract | E38: Clay swelling and dispersion begin due to Na+ and K+ presence; moderate reduction in soil permeability. | F38: Apply agricultural gypsum (CaSO4) to replace dispersive Na+ and K+ with flocculating Ca2+. | G38: FAO & ICBA (2023) / WASAG Farmers' Guidelines (Tabel 6 & 7); gebaseerd op Rengasamy & Marchuk (2011)
A39: CROSS | B39: > 20.0 (mmol/L)^0.5 | C39: Severely Sodic | D39: Lab ICP/AAS test of Na+, K+, Ca2+, Mg2+ in saturation extract | E39: Complete clay dispersion, aggregate collapse, and pore blockage; impenetrable surface crusting. | F39: Mandatory: Apply heavy split doses of Gypsum (CaSO4) BEFORE freshwater leaching to prevent total structural seal. | G39: FAO & ICBA (2023) / WASAG Farmers' Guidelines (Tabel 6 & 7); gebaseerd op Rengasamy & Marchuk (2011)
A40: ASSUMPTIONS & CONSIDERATIONS FOR CROSS: Assumption: Assumes CROSS provides superior prediction of clay dispersion over SAR by incorporating K+ dispersion and Mg2+ vs Ca2+ flocculation power. Critical Consideration: CROSS requires full cation analysis (ICP/AAS), which increases laboratory testing cost compared to standard SAR titration.
A42: TABLE 6: SODICITY RISK — SAR (SODIUM ADSORPTION RATIO)
A43: Parameter Name | B43: Value / Range | C43: Classification / Class | D43: Field / Lab Measurement Method | E43: Agronomic & Soil Physical Impact | F43: Immediate Action / Protocol | G43: Scientific Source & Grounding
A44: SAR | B44: < 13.0 (mmol/L)^0.5 | C44: Non-Sodic | D44: Lab titration/spectrophotometry of Na+, Ca2+, Mg2+ in saturation extract | E44: Clay platelets remain stable and flocculated; normal soil structure and water infiltration. | F44: No chemical amelioration required; maintain standard physical water management. | G44: Richards (1954); Van Hoorn & Van Alphen (1994)
A45: SAR | B45: ≥ 13.0 (mmol/L)^0.5 | C45: Sodic (Alkali) | D45: Lab titration/spectrophotometry of Na+, Ca2+, Mg2+ in saturation extract | E45: Diffuse double layer expands, causing clay dispersion, aggregate collapse, and surface sealing. | F45: Mandatory: Apply Gypsum (CaSO4) BEFORE freshwater leaching to replace exchangeable Na+ with Ca2+. | G45: Richards (1954); Abrol et al. (1988)
A46: ASSUMPTIONS & CONSIDERATIONS FOR SAR: Assumption: Assumes clay platelets remain structurally stable if SAR < 13, dispersing only when SAR ≥ 13. Critical Consideration: In highly weathered soils or under irrigation with very low-salinity water, structural collapse can occur at SAR as low as 6.
A48: TABLE 7: SODICITY RISK — ESP (EXCHANGEABLE SODIUM PERCENTAGE)
A49: Parameter Name | B49: Value / Range | C49: Classification / Class | D49: Field / Lab Measurement Method | E49: Agronomic & Soil Physical Impact | F49: Immediate Action / Protocol | G49: Scientific Source & Grounding
A50: ESP | B50: < 15% | C50: Non-Sodic | D50: Lab ammonium acetate extraction for exchangeable cations and CEC | E50: Clay platelets remain stable and flocculated; excellent soil structural stability and water infiltration. | F50: No chemical amendments required; focus on standard agronomy and salt leaching. | G50: Richards (1954)
A51: ESP | B51: 15% – 30% | C51: Moderately Sodic | D51: Lab ammonium acetate extraction for exchangeable cations and CEC | E51: Clay swelling and dispersion begin to occur; soil aggregates break down; moderate permeability loss. | F51: Apply landbouw gips (CaSO4) to replace adsorbed sodium with calcium. Ensure adequate leaching to flush Na+. | G51: Richards (1954); Van Hoorn & Van Alphen (1994)
A52: ESP | B52: > 30% | C52: Severely Sodic | D52: Lab ammonium acetate extraction for exchangeable cations and CEC | E52: Complete structural collapse; total loss of soil infiltration and water conductivity; toxic sodium levels. | F52: Immediate, intensive agricultural gypsum and acid application required. Split doses over multiple seasons. | G52: Richards (1954); Abrol et al. (1988)
A53: ASSUMPTIONS & CONSIDERATIONS FOR ESP: Assumption: Assumes ESP is directly correlated with SAR via the empirical USDA relation (ESP ≈ SAR for SAR 2–30). Critical Consideration: Direct laboratory ESP measurement requires ammonium acetate CEC extraction, which is slow and prone to errors in saline soils.
A55: TABLE 8: IRRIGATION WATER SALINITY (ECw)
A56: Parameter Name | B56: Value / Range | C56: Classification / Class | D56: Field / Lab Measurement Method | E56: Agronomic & Soil Physical Impact | F56: Immediate Action / Protocol | G56: Scientific Source & Grounding
A57: ECw | B57: < 0.7 dS/m | C57: No Restriction | D57: Direct field measurement of water source with EC meter | E57: Safe, high-quality water; no osmotic stress on plants and extremely low risk of soil salinization. | F57: Standard irrigation scheduling; no leaching adjustments needed. | G57: Ayers & Westcot (1985)
A58: ECw | B58: 0.7 – 3.0 dS/m | C58: Slight to Moderate Restriction | D58: Direct field measurement of water source with EC meter | E58: Soluble salts gradually accumulate in active root zone, causing moderate crop water stress over time. | F58: Increase irrigation depth using Leaching Fraction (LF = ECw / [5*ECe - ECw]) to flush salts below root zone. | G58: Ayers & Westcot (1985); Van Hoorn & Van Alphen (1994)
A59: ECw | B59: > 3.0 dS/m | C59: Severe Restriction | D59: Direct field measurement of water source with EC meter | E59: Acute osmotic drought, rapid salt accumulation in root zone, and severe leaf foliar burn if sprinkler-applied. | F59: Mix with fresh water (Conjunctive Use), restrict to drip irrigation, select tolerant crops, ensure artificial drainage. | G59: Ayers & Westcot (1985); Doneen (1954)
A60: ASSUMPTIONS & CONSIDERATIONS FOR ECw: Assumption: Assumes a standard moderate Leaching Fraction (LF) of 15% is continuously maintained under conventional surface irrigation. Critical Consideration: High-efficiency localized drip systems without dedicated leaching cause rapid salt accumulation at wet bulb edges.
A62: TABLE 9: IRRIGATION WATER SALINITY (TDS FALLBACK)
A63: Parameter Name | B63: Value / Range | C63: Classification / Class | D63: Field / Lab Measurement Method | E63: Agronomic & Soil Physical Impact | F63: Immediate Action / Protocol | G63: Scientific Source & Grounding
A64: TDS | B64: < 450 mg/L (ppm) | C64: No Restriction | D64: Gravimetric drying of water sample or TDS meter | E64: Low dissolved salt concentration; negligible hazard to crops and soil structure. | F64: Standard water management practices; no special leaching required. | G64: Doneen (1954)
A65: TDS | B65: 450 – 2000 mg/L | C65: Slight to Moderate Restriction | D65: Gravimetric drying of water sample or TDS meter | E65: Moderate salt load; potential gradual soil salinization depending on soil texture and drainage. | F65: Apply moderate leaching fraction and monitor soil ECe. Convert TDS to ECw via TDS ≈ 640 * ECw. | G65: Doneen (1954); Karimzadeh et al. (2024)
A66: TDS | B66: > 2000 mg/L | C66: Severe Restriction | D66: Gravimetric drying of water sample or TDS meter | E66: High salt load; causes severe osmotic stress and rapid salt buildup in topsoil. | F66: Restricted to salt-tolerant crops; requires conjunctive water blending or high leaching fractions. | G66: Doneen (1954); Van Straten et al. (2019)
A67: ASSUMPTIONS & CONSIDERATIONS FOR TDS: Assumption: Assumes a constant empirical conversion factor (TDS ≈ 640 * ECw) for converting solute mass to electrical conductivity. Critical Consideration: Conversion factor varies between 550 and 900 depending on dominant chemical ions (sulfates vs chlorides).
A69: TABLE 10: GROUNDWATER DEPTH (WATER TABLE / GWS)
A70: Parameter Name | B70: Value / Range | C70: Classification / Class | D70: Field / Lab Measurement Method | E70: Agronomic & Soil Physical Impact | F70: Immediate Action / Protocol | G70: Scientific Source & Grounding
A71: Water Table Depth | B71: > 2.0 m | C71: Safe Depth | D71: Regular measurement in field observation wells or piezometers | E71: Groundwater table stands below critical capillary zone; no risk of capillary salt transport into root zone. | F71: Maintain current natural or artificial drainage. Monitor water table levels seasonally. | G71: Ritzema (1994); Wang et al. (2022)
A72: Water Table Depth | B72: 1.5 – 2.0 m | C72: Moderate Risk | D72: Regular measurement in field observation wells or piezometers | E72: Capillary rise begins to reach subsoil during dry periods, slowly carrying dissolved salts upward. | F72: Monitor shallow piezometers closely. Plan subsoil drainage spacing design to prepare for potential water table rise. | G72: Ritzema (1994); Bhutta & Smedema (2007)
A73: Water Table Depth | B73: < 1.5 m | C73: Critical (Waterlogged) | D73: Regular measurement in field observation wells or piezometers | E73: Severe waterlogging; rapid capillary rise and evaporation form heavy surface salt crusts within days. | F73: Mandatory: Install Subsurface Pipe Drainage (SPD) or deep open ditches to lower and control water table. | G73: Ritzema (1994); Bhutta & Smedema (2007)
A74: ASSUMPTIONS & CONSIDERATIONS FOR WATER TABLE DEPTH: Assumption: Assumes a groundwater table deeper than 2.0 m is completely safe from capillary salinization. Critical Consideration: Critical depth depends on soil texture; in fine silts and silty clays, capillary forces pull water upward from 2.5 to 3.0 m.
A76: TABLE 11: GROUNDWATER SALINITY (ECgw)
A77: Parameter Name | B77: Value / Range | C77: Classification / Class | D77: Field / Lab Measurement Method | E77: Agronomic & Soil Physical Impact | F77: Immediate Action / Protocol | G77: Scientific Source & Grounding
A78: ECgw | B78: < 1.5 dS/m | C78: Fresh / Low Risk | D78: Direct conductivity measurement of groundwater sample | E78: Low salt content in shallow groundwater; capillary rise poses minimal salinization risk. | F78: Standard groundwater monitoring; safe for sub-irrigation if water table is controlled. | G78: Bhutta & Smedema (2007)
A79: ECgw | B79: 1.5 – 5.0 dS/m | C79: Brackish / Moderate Risk | D79: Direct conductivity measurement of groundwater sample | E79: Moderate salt content; capillary rise will deposit substantial salts in rootzone if water table < 1.5 m. | F79: Control water table depth below 1.5 m via tile drainage; apply periodic leaching irrigation. | G79: Bhutta & Smedema (2007); Liu et al. (2025)
A80: ECgw | B80: > 5.0 dS/m | C80: Highly Saline / Severe Risk | D80: Direct conductivity measurement of groundwater sample | E80: Extreme salt content; capillary rise causes severe secondary salinization and total crop failure. | F80: Mandatory water table drawdown below critical depth (> 2.0 m) using subsurface drainage. | G80: Bhutta & Smedema (2007); Liu et al. (2026)
A81: ASSUMPTIONS & CONSIDERATIONS FOR GROUNDWATER SALINITY: Assumption: Assumes groundwater salinity remains static across seasons during water table fluctuations. Critical Consideration: Groundwater salinity exhibits strong seasonal dynamics due to monsoon recharge, irrigation deep percolation, and evaporation.
A83: TABLE 12: HYDRAULIC CONDUCTIVITY (K-VALUE)
A84: Parameter Name | B84: Value / Range | C84: Classification / Class | D84: Field / Lab Measurement Method | E84: Agronomic & Soil Physical Impact | F84: Immediate Action / Protocol | G84: Scientific Source & Grounding
A85: K-value | B85: > 2.0 m/day | C85: Rapid to Very Rapid | D85: In-situ auger-hole method below water table or infiltrometer | E85: Water moves very rapidly through soil; high leaching capacity; waterlogging risk is negligible. | F85: No drainage spacing restriction. Highly suitable for rapid flushing. Apply small, frequent irrigation gifts. | G85: Ritzema (1994)
A86: K-value | B86: 0.5 – 2.0 m/day | C86: Moderate | D86: In-situ auger-hole method below water table or infiltrometer | E86: Standard horizontal and vertical water movement; optimal for agricultural drainage and plant growth. | F86: Standard subsurface pipe drainage design; standard spacing formulas (Hooghoudt) apply. | G86: Ritzema (1994); Van Hoorn & Van Alphen (1994)
A87: K-value | B87: 0.1 – 0.5 m/day | C87: Moderately Slow | D87: In-situ auger-hole method below water table or infiltrometer | E87: Downward water movement is restricted; high risk of perched water tables and temporary waterlogging. | F87: Requires narrower drain pipe spacing (closer pipes) to be effective. Incorporate deep-rooting cover crops. | G87: Ritzema (1994); Liu et al. (2025)
A88: K-value | B88: < 0.1 m/day | C88: Slow to Very Slow | D88: In-situ auger-hole method below water table or infiltrometer | E88: Water stagnates; extremely high waterlogging risk. Reclamation leaching becomes extremely slow and difficult. | F88: Requires very close drain spacing, mole drainage, or deep mechanical ripping combined with gypsum. | G88: Ritzema (1994); Abrol et al. (1988)
A89: ASSUMPTIONS & CONSIDERATIONS FOR K-VALUE: Assumption: Assumes soil profile is homogeneous and isotropic, allowing water movement calculations via steady-state drainage equations (Hooghoudt). Critical Consideration: In-situ K-values naturally vary by orders of magnitude across a field; requires dense grid sampling for reliable pipe spacing design.
A91: TABLE 13: SOIL TEXTURE & LAYERING
A92: Parameter Name | B92: Value / Range | C92: Classification / Class | D92: Field / Lab Measurement Method | E92: Agronomic & Soil Physical Impact | F92: Immediate Action / Protocol | G92: Scientific Source & Grounding
A93: Soil Texture | B93: Coarse (Sand, Loamy Sand) | C93: High Permeability | D93: Laboratory sieve and hydrometer/pipette analysis | E93: Rapid water infiltration; low water and nutrient holding capacity; very low hazard of sodic structural decay. | F93: Apply high leaching efficiency (rapid flushing). Require frequent, small water applications (drip) to avoid deep percolation. | G93: Richards (1954)
A94: Soil Texture | B94: Medium (Loam, Silt Loam, Sandy Loam) | C94: Optimal Balance | D94: Laboratory sieve and hydrometer/pipette analysis | E94: Balanced water retention and infiltration. Optimal physical environment for root development and salt leaching. | F94: Use standard leaching calculations and schedules. Maintain regenerative farming to protect aggregate structure. | G94: Richards (1954); Liu et al. (2025)
A95: Soil Texture | B95: Fine (Clay, Silty Clay, Clay Loam) | C95: Low Permeability | D95: Laboratory sieve and hydrometer/pipette analysis | E95: Extremely slow infiltration; highly prone to soil compaction, crusting, and waterlogging. High risk of sodic swelling. | F95: Requires careful leaching rates to avoid ponding. Apply structural organic amendments and gypsum to promote aggregation. | G95: Richards (1954); Abrol et al. (1988)
A96: Soil Texture | B96: Stratified (Clay pans / Plow pans) | C96: Physical Barrier | D96: Field soil auger profile logging and horizon description | E96: Blocks downward water percolation; creates perched water tables; traps salts in upper root zone. | F96: Perform periodic subsoiling (deep mechanical ripping) to physically break hardpan layer and restore drainage connectivity. | G96: Van Hoorn & Van Alphen (1994); Liu et al. (2025)
A97: ASSUMPTIONS & CONSIDERATIONS FOR SOIL TEXTURE: Assumption: Assumes water, air, and salt transport are uniform throughout the root zone based on dominant soil texture class. Critical Consideration: Abrupt vertical stratifications (such as clay pans, hardpans, or plow pans) act as physical flow barriers, halting vertical drainage.
A99: TABLE 14: MICRO-TOPOGRAPHY & SLOPE
A100: Parameter Name | B100: Value / Range | C100: Classification / Class | D100: Field / Lab Measurement Method | E100: Agronomic & Soil Physical Impact | F100: Immediate Action / Protocol | G100: Scientific Source & Grounding
A101: Micro-topography | B101: Flat (< 0.1% slope) with depressions | C101: Uneven Surface | D101: RTK-GPS topographic survey or optical leveling | E101: Water pools in low spots, causing local waterlogging, while high spots remain dry and experience intense capillary salinization. | F101: Perform Laser Land Leveling (LLL) to achieve a uniform micro-flat surface, ensuring uniform water and salt leaching. | G101: Savva & Frenken (2002)
A102: Micro-topography | B102: Gentle Slope (0.1% – 1.0%) | C102: Optimal Surface Drainage | D102: RTK-GPS topographic survey or optical leveling | E102: Water flows slowly and evenly without causing soil erosion, promoting uniform water infiltration. | F102: Highly suitable for furrow, strip, or basin surface irrigation; standard field management. | G102: Savva & Frenken (2002); Singh (2019)
A103: Micro-topography | B103: Moderate to Steep (> 1.0%) | C103: Erosion Hazard / Restricted Surface | D103: RTK-GPS topographic survey or optical leveling | E103: High water runoff velocity; causes severe soil erosion; low infiltration time prevents effective salt leaching. | F103: Shift completely to pressurized irrigation (drip or micro-sprinkler) or implement contour terracing. | G103: Savva & Frenken (2002)
A104: ASSUMPTIONS & CONSIDERATIONS FOR TOPOGRAPHY: Assumption: Assumes fields with slopes exceeding 1.0% are highly restrictive due to severe runoff and erosion risks during surface flood irrigation. Critical Consideration: Terrain slope limitation disappears under pressurized irrigation (drip or sprinkler), which applies water below infiltration capacity.
A106: TABLE 15: CATION EXCHANGE CAPACITY (CEC)
A107: Parameter Name | B107: Value / Range | C107: Classification / Class | D107: Field / Lab Measurement Method | E107: Agronomic & Soil Physical Impact | F107: Immediate Action / Protocol | G107: Scientific Source & Grounding
A108: CEC | B108: < 10 meq/100g (cmol/kg) | C108: Low Buffer Capacity | D108: Lab ammonium acetate distillation at pH 7.0 | E108: Typical for coarse sandy soils; low ability to adsorb cations; very easy to reclaim but poor nutrient holding capacity. | F108: Low total gypsum requirement (tons/ha) even if ESP is high, but requires frequent organic matter additions to hold nutrients. | G108: Richards (1954)
A109: CEC | B109: 10 – 20 meq/100g (cmol/kg) | C109: Medium Buffer Capacity | D109: Lab ammonium acetate distillation at pH 7.0 | E109: Typical for medium loam and silt loam soils; balanced chemical buffering and nutrient retention. | F109: Standard gypsum requirement calculations apply. Split doses are generally unnecessary. | G109: Richards (1954); Van Hoorn & Van Alphen (1994)
A110: CEC | B110: > 20 meq/100g (cmol/kg) | C110: High Buffer Capacity | D110: Lab ammonium acetate distillation at pH 7.0 | E110: Typical for fine clay soils; extremely high capacity to hold exchangeable sodium, making them highly resistant to reclamation. | F110: High gypsum requirement (tons/ha). Requires split gypsum applications (e.g. 5–10 t/ha per season) with extensive leaching. | G110: Richards (1954); Abrol et al. (1988)
A111: ASSUMPTIONS & CONSIDERATIONS FOR CEC: Assumption: Assumes CEC is a static chemical buffering capacity that dictates the exact calcium dose required to displace exchangeable sodium. Critical Consideration: Standard laboratory CEC measurements in saline-sodic soils are prone to errors due to interference of soluble salts and native carbonates.
A113: TABLE 16: SOIL BULK DENSITY (ρb)
A114: Parameter Name | B114: Value / Range | C114: Classification / Class | D114: Field / Lab Measurement Method | E114: Agronomic & Soil Physical Impact | F114: Immediate Action / Protocol | G114: Scientific Source & Grounding
A115: Bulk Density | B115: < 1.4 g/cm³ | C115: Healthy / Uncompacted | D115: Undisturbed soil core ring sampling (dried at 105°C and weighed) | E115: Excellent soil pore space, aeration, and root penetration; normal water infiltration and drainage. | F115: Maintain soil organic matter and avoid heavy machinery traffic when soil is wet. No mechanical remediation needed. | G115: Richards (1954); Liu et al. (2025)
A116: Bulk Density | B116: 1.4 – 1.6 g/cm³ | C116: Moderately Compacted | D116: Undisturbed soil core ring sampling (dried at 105°C and weighed) | E116: Restricted pore space; slower infiltration rates and moderately impaired root development. | F116: Incorporate deep-rooting cover crops, apply organic compost, and restrict tillage to restore soil porosity. | G116: Liu et al. (2025)
...

Sheet Section C - Measure Selection
A1: GLOBAL SALINIZATION MANAGEMENT MEASURES FRAMEWORK
A2: Comprehensive taxonomy of prevention, mitigation, remediation, and adaptation measures backed by scientific literature
A3: Category | B3: Measure Name | C3: 🎯 Strategic Goal | D3: 💰 Budget Class | E3: 📍 Spatial Scale | F3: ⏳ Time Horizon | G3: 🏷️ Applicable Soil/Water Condition | H3: ⚠️ Effluent & Env. Risk | I3: ⚙️ Operational Complexity | J3: What It Is (Description) | K3: How It Works (Mechanism) | L3: What It Does (Impact & Outcome) | M3: 💵 Quantitative Cost Estimate (€ / $ per ha or unit) | N3: 📚 Scientific References & Literature Sources | O3: 🚦 Dynamic Suitability / Potential Measure Status | P3: ✅ Select Measure? (User Dropdown)
A4: 🏗️ Physical & Hydrological Engineering | B4: Subsurface Pipe Drainage (SPD) | C4: Mitigation / Remediation | D4: High budget | E4: Farm level | F4: Long term | G4: Saline Soil / Shallow Water Table | H4: High (saline discharge) | I4: Medium | J4: Installed network of corrugated perforated plastic pipes (1.0–1.8 m depth, 15–50 m spacing). | K4: Intercepts rising groundwater and flushes saline soil water to collectors via hydraulic gradient. | L4: Lowers soil ECe below crop thresholds, prevents waterlogging, enables active root zone leaching. | M4: ~$1,000 – $3,500 / ha (capital install; varies by pipe spacing & envelope material) | N4: Ritzema et al. (2023); Singh (2019, 2021); Han et al. (2023); SWAT-Salt China Study (2025) | O4: =IF(AND(fa_GWD="",fa_ECe=""), "🟠 DATA NEEDED — measure water table depth (B9) and ECe (B6)", IF(OR(AND(ISNUMBER(fa_GWD),fa_GWD<2),AND(ISNUMBER(fa_ECe),fa_ECe>=4)), "🟢 RECOMMENDED — water table < 2.0m or ECe ≥ 4.0: leachate needs an outlet", "🔴 NOT RECOMMENDED — deep water table and ECe < 4: no drainage constraint")) -> 🟠 DATA NEEDED — measure water table depth (B9) and ECe (B6) | P4: Not Selected
A5: 🏗️ Physical & Hydrological Engineering | B5: Open Ditch Drainage | C5: Mitigation / Remediation | D5: Medium budget | E5: Farm level | F5: Long term | G5: Waterlogged / Shallow Water Table | H5: Medium-High (saline runoff) | I5: High | J5: Open channels and collection ditches surrounding or intersecting agricultural fields. | K5: Collects excess surface runoff and shallow groundwater seepage by natural gravity flow. | L5: Regulates water table depth and evacuates leachates; lower initial cost than pipe drainage but costs 5–15% arable land and needs frequent dredging. | M5: ~$400 – $1,200 / ha (excavation + land loss cost) | N5: Tanji & Kielen (2002); Singh (2019); Dandekar & Chougule (2010) | O5: =IF(fa_GWD="", "🟠 DATA NEEDED — measure water table depth (B9)", IF(fa_GWD<2, "🟢 RECOMMENDED — water table < 2.0m: gravity drainage as low-cost alternative", "🔴 NOT RECOMMENDED — water table ≥ 2.0m: nothing to drain")) -> 🟠 DATA NEEDED — measure water table depth (B9) | P5: Not Selected
A6: 🏗️ Physical & Hydrological Engineering | B6: Vertical Drainage / Tubewells | C6: Mitigation / Remediation | D6: High budget | E6: Regional / National level | F6: Long term | G6: Deep Permeable Aquifers / Waterlogging | H6: Very High (large saline volume) | I6: High | J6: Deep groundwater pumping wells equipped with high-capacity electric/diesel pumps. | K6: Pumps deep saline or brackish groundwater continuously to depress the regional hydraulic head. | L6: Suppresses capillary rise over large regional areas (e.g. SCARP projects). Requires permeable deep aquifers and high ongoing energy costs. | M6: ~$15,000 – $40,000 per well station (~$500–$1,200/ha cap. + $150–$300/ha/yr energy) | N6: Qadir et al. (2014); Pakistan SCARP Review Reports; Singh (2021) | O6: =IF(fa_GWD="", "🟠 DATA NEEDED — measure water table depth (B9)", IF(fa_GWD<1.5, "🟢 RECOMMENDED — water table < 1.5m: regional pumping; verify aquifer", "🔴 NOT RECOMMENDED — water table ≥ 1.5m: regional pumping not justified")) -> 🟠 DATA NEEDED — measure water table depth (B9) | P6: Not Selected
A7: 🏗️ Physical & Hydrological Engineering | B7: Canal Lining | C7: Prevention | D7: High budget | E7: Regional / National level | F7: Long term | G7: Secondary Salinization via Seepage | H7: Low (prevents seepage) | I7: Low-Medium | J7: Sealing unlined earthen irrigation canals with concrete, geomembranes, or compacted clay. | K7: Eliminates water seepage through canal beds and banks into adjacent unconfined aquifers. | L7: Stops canal seepage—the primary driver of rising regional water tables and secondary salinization in dryland irrigation schemes. | M7: ~$15 – $45 / m² lined area (~$2,000–$8,000 / km canal length depending on cross-section) | N7: Wichelns (1999); Tanji & Kielen (2002); Singh (2021) | O7: =IF(fa_GWD="", "🟠 DATA NEEDED — measure water table depth (B9)", IF(fa_GWD<2, "🟢 RECOMMENDED — water table < 2.0m: rising table points to seepage", "🔵 NO-REGRET — preventive; no rising water table detected right now")) -> 🟠 DATA NEEDED — measure water table depth (B9) | P7: Not Selected
A8: 🏗️ Physical & Hydrological Engineering | B8: Deep Ripping / DVRT (Deep Vertical Rotary Tillage) | C8: Mitigation / Remediation | D8: Low budget | E8: Farm level | F8: Short term | G8: Soil Hardpan / Dense Compaction | H8: Low (in-situ structural) | I8: Low | J8: Subsoiling operation using deep rigid tines or rotary subsoilers (40–60 cm depth) without topsoil inversion. | K8: Mechanically shatters dense subsoil hardpans and plough pans beneath the topsoil layer. | L8: Restores vertical hydraulic conductivity, breaks capillary rise pathways, and facilitates downward salt leaching. | M8: ~$80 – $250 / ha per treatment (machinery, fuel, operator) | N8: Chen et al. (2021); Agric. Water Manag. (2025); Stavi et al. (2021) | O8: =IF(AND(fa_SOD="",fa_pH=""), "🟠 DATA NEEDED — measure sodicity (B7) and pH (B5)", IF(fa_SOD="", IF(fa_pH>=8.5, "🟠 DATA NEEDED — sodicity not measured and pH alone is not conclusive: confirm CROSS/SAR (B7) before ripping", "🔵 NO-REGRET — only worthwhile if a compaction pan is confirmed in the field"), IF(fa_SODIC=1, "🟢 RECOMMENDED — SAR ≥ 13: shatter the dispersed crust and pan", "🔵 NO-REGRET — only worthwhile if a compaction pan is confirmed in the field"))) -> 🟠 DATA NEEDED — measure sodicity (B7) and pH (B5) | P8: Not Selected
A9: 🏗️ Physical & Hydrological Engineering | B9: Precision Land Leveling (Laser Grading) | C9: Prevention / Mitigation | D9: Low budget | E9: Farm level | F9: Short term | G9: Surface Irrigated Fields (Uneven) | H9: Low (enhances efficiency) | I9: Low | J9: High-precision field grading using GPS or laser-guided earthmoving equipment. | K9: Ensures uniform distribution and infiltration of applied irrigation or rainfall water across the field. | L9: Eliminates waterlogged low spots and prevents dry high spots where intense evaporation causes salt 'hotspots'. | M9: ~$120 – $350 / ha (performed every 3–5 years) | N9: Ashraf & Saeed (2006); Panagea et al. (2016); Singh (2021) | O9: =IF(fa_TOPO="", "🟠 DATA NEEDED — survey micro-topography (B12)", IF(fa_TOPO>=5, "🟢 RECOMMENDED — elevation spread ≥ 5 cm: level out salt scalds", "🔵 NO-REGRET — field is level; re-check every 3–5 years")) -> 🟠 DATA NEEDED — survey micro-topography (B12) | P9: Not Selected
A10: 🏗️ Physical & Hydrological Engineering | B10: Forced Leaching Regime | C10: Remediation | D10: Low to Medium budget | E10: Farm level | F10: Short term | G10: Saline Soil (ECe > 4 dS/m) | H10: Medium-High (flushes salts downstream) | I10: Medium | J10: Applying excess high-quality fresh water (leaching fraction: 150–450 mm) during off-season or winter. | K10: Dissolves accumulated soluble salts in the topsoil and flushes them downward below the active root zone into drains. | L10: Rapidly reduces root zone ECe below crop toxicity thresholds; requires functional drainage and fresh water availability. | M10: ~$100 – $400 / ha per leaching event (water supply + pumping energy cost) | N10: FAO Paper 29; Hanson et al. (2008); SWAT-Salt China Study (2025) | O10: =IF(AND(fa_ECe="",fa_SODIC=""), "🟠 DATA NEEDED — measure soil ECe (B6) and Sodicity (B7/B5)", IF(fa_SODIC=1, IF(fa_SOD="", "🔴 UNSAFE NOW — probably sodic (pH > 8.5, CROSS/SAR not measured): apply gypsum first, then leach (leaching trap)", "🔴 UNSAFE NOW — sodic soil: apply gypsum/acid first, then leach (leaching trap)"), IF(AND(ISNUMBER(fa_ECe),fa_ECe>=4), IF(fa_SODIC="", "🟠 DATA NEEDED — ECe ≥ 4.0 but sodicity not measured: measure CROSS/SAR (B7) before leaching", "🟢 RECOMMENDED — ECe ≥ 4.0 and not sodic: flush salts below the root zone"), "🔴 NOT RECOMMENDED — ECe < 4.0: no salt load to flush, wastes water"))) -> 🟠 DATA NEEDED — measure soil ECe (B6) and Sodicity (B7/B5) | P10: Not Selected
A11: 🧪 Chemical & Soil Amelioration | B11: Gypsum Application (CaSO4·2H2O) | C11: Remediation | D11: Low to Medium budget | E11: Farm level | F11: Medium term | G11: Sodic Soil (pH > 8.5, ESP > 15%) | H11: Low-Medium (displaces Na+) | I11: Low | J11: Spreading and incorporating agricultural gypsum into sodic or saline-sodic soils. | K11: Calcium (Ca²⁺) ions displace exchangeable sodium (Na⁺) adsorbed on clay particle exchange sites. | L11: Restores soil aggregation, porosity, and hydraulic conductivity (flocculation), allowing displaced sodium to be leached out safely. | M11: ~$200 – $800 / ha (based on 3–10 t/ha gift @ $50–$80/tonne incl. spreading) | N11: Qadir et al. (2007, 2014); Sumner & Naidu (1998); Schoonover method studies | O11: =IF(AND(fa_SOD="",fa_pH=""), "🟠 DATA NEEDED — measure sodicity (B7) and pH (B5)", IF(fa_SOD="", IF(fa_SODIC=1, "🟢 RECOMMENDED (PROVISIONAL) — pH > 8.5 suggests sodicity, CROSS/SAR not measured: gypsum advised with uncertainty, confirm (B7)", "🟠 DATA NEEDED — pH ≤ 8.5 does not show whether the soil is sodic: measure CROSS/SAR (B7)"), IF(fa_SODIC=1, "🟢 RECOMMENDED — SAR ≥ 13: sodium has to be displaced before leaching", "🔴 NOT RECOMMENDED — soil is not sodic: gypsum only adds salt"))) -> 🟠 DATA NEEDED — measure sodicity (B7) and pH (B5) | P11: Not Selected
A12: 🧪 Chemical & Soil Amelioration | B12: Soil Acidification (Elemental Sulfur / Acid Injection) | C12: Remediation | D12: Low to Medium budget | E12: Farm level | F12: Medium term | G12: High-pH Calcareous Sodic Soil (pH > 8.5) | H12: Low-Medium (mobilizes ions) | I12: Medium-High | J12: Applying elemental sulfur (S⁰) or injecting dilute sulfuric acid into high-pH calcareous soils. | K12: Soil bacteria oxidize sulfur to sulfuric acid, neutralizing Na2CO3/NaHCO3 and dissolving soil calcite (CaCO3) to release free Ca²⁺. | L12: Rapidly lowers extreme soil pH (>8.5) and mobilizes native calcium to displace exchangeable sodium. | M12: ~$300 – $1,100 / ha (0.5–2 t/ha S⁰ @ $400–$700/tonne; acid injection requires specialized rig) | N12: Qadir et al. (2007); Litalien & Zeeb (2020); FAO Salinity Manuals | O12: =IF(OR(fa_pH="", fa_LIME=""), "🟠 DATA NEEDED — measure soil pH (B5) and native lime (B17)", IF(AND(fa_pH>=8.5, fa_LIME>0), IF(fa_SOD="", "🟠 DATA NEEDED — sodicity not measured and pH alone is not conclusive: confirm CROSS/SAR (B7); gypsum is the provisional option", IF(fa_SODIC=1, "🟢 RECOMMENDED — pH ≥ 8.5 and native lime > 0%: acid frees native Ca²⁺", "🔴 NOT RECOMMENDED — measured SAR < 13: soil is not sodic, no calcium release needed")), "🔴 NOT RECOMMENDED — pH < 8.5 or no native lime: use gypsum instead")) -> 🟠 DATA NEEDED — measure soil pH (B5) and native lime (B17) | P12: Not Selected
A13: 🧪 Chemical & Soil Amelioration | B13: Organic Amendments (Compost, Manure, Biochar) | C13: Mitigation / Remediation | D13: Low to Medium budget | E13: Farm level | F13: Medium term | G13: Degraded Saline / Sodic Soil | H13: Very Low (environmentally safe) | I13: Low | J13: Incorporating compost, animal manure, crop residues, or biochar into the topsoil layer. | K13: Enriches organic carbon, enhances Cation Exchange Capacity (CEC), improves soil aggregation, and stimulates microbial activity. | L13: Buffers osmotic stress on plant roots, increases soil water holding capacity, and reduces Na⁺ toxicity via organic complexation. | M13: ~$250 – $900 / ha (compost/manure 10–30 t/ha @ $20–$40/t; biochar higher unit cost) | N13: Setia et al. (2013); Sun et al. (2019); Sahab et al. (2021); Amelung et al. (2020) | O13: =IF(AND(fa_SOD="",fa_ECe=""), "🟠 DATA NEEDED — measure sodicity (B7) and ECe (B6)", IF(OR(AND(ISNUMBER(fa_SOD),fa_SODIC=1),AND(ISNUMBER(fa_ECe),fa_ECe>=4)), "🟢 RECOMMENDED — SAR ≥ 13 or ECe ≥ 4.0: buffers osmotic stress and rebuilds structure", "🔵 NO-REGRET — raises CEC and water holding capacity in any soil")) -> 🟠 DATA NEEDED — measure sodicity (B7) and ECe (B6) | P13: Not Selected
A14: 🧪 Chemical & Soil Amelioration | B14: Irrigation Water Acidification | C14: Mitigation | D14: Low budget | E14: Farm level | F14: Short term | G14: High-Bicarbonate Irrigation Water | H14: Low (dilute acid, closed system) | I14: Medium | J14: Injecting mild acids (sulfuric, nitric, or phosphoric acid) into pressurized drip/sprinkler irrigation water. | K14: Adjusts irrigation water pH to 6.0–6.5 and neutralizes toxic bicarbonate (HCO3⁻) ions. | L14: Prevents bicarbonate accumulation in the root zone and eliminates mineral/scale clogging in drip emitters. | M14: ~$50 – $200 / ha / season (acid chemical injection kit + reagent consumption) | N14: Hanson (2012); Botía et al. (2005); Horticulturae (2017) | O14: =IF(fa_RSC="", "🟠 DATA NEEDED — measure water RSC (B16)", IF(fa_RSC>2.5, "🟢 RECOMMENDED — RSC > 2.5 meq/L: neutralise bicarbonate", "🔴 NOT RECOMMENDED — RSC ≤ 2.5 meq/L: no bicarbonate hazard")) -> 🟠 DATA NEEDED — measure water RSC (B16) | P14: Not Selected
A15: 🌱 Agronomic & Biosaline Adaptation | B15: Mulched Drip Irrigation (MDI) | C15: Prevention / Mitigation | D15: Medium budget | E15: Farm level | F15: Short term | G15: Arid / Semi-Arid Row Crops | H15: Medium (film waste / inter-row salt) | I15: Medium | J15: Combining surface/subsurface drip irrigation with plastic film (PE) or organic surface mulching. | K15: Shields the soil surface from direct solar radiation and wind, driving soil evaporation to near zero. | L15: Prevents capillary salt rise into the root zone while conserving moisture; note: inter-row strips require periodic flushing. | M15: ~$800 – $2,200 / ha setup + ~$200–$400/ha/yr for plastic film replacement | N15: Wang et al. (2018, Eur. J. Soil Sci.); Wang et al. (2020); Karimzadeh et al. (2024) | O15: =IF(AND(fa_ECe="",fa_ECw=""), "🟠 DATA NEEDED — measure soil ECe (B6) and irrigation ECw (B8)", IF(OR(AND(ISNUMBER(fa_ECe),fa_ECe>=4),AND(ISNUMBER(fa_ECw),fa_ECw>=0.7)), "🟢 RECOMMENDED — ECe ≥ 4.0 or ECw ≥ 0.7: salt load present, mulch keeps it off surface", "🔵 NO-REGRET — saves water in an arid climate even without a salt problem")) -> 🟠 DATA NEEDED — measure soil ECe (B6) and irrigation ECw (B8) | P15: Not Selected
A16: 🌱 Agronomic & Biosaline Adaptation | B16: Biosaline Agriculture & Salt-Tolerant Crops | C16: Adaptation | D16: Low budget | E16: Farm level | F16: Short term | G16: Saline Soil (ECe 4–16+ dS/m) / Brackish Water | H16: Very Low (no effluent) | I16: Low | J16: Cultivating salt-tolerant crop varieties (e.g. barley, sugarbeet, quinoa, triticale) or halophytes (e.g. Salicornia). | K16: Utilizes physiological plant adaptations including Na⁺ exclusion, osmoregulation, and vacuolar salt sequestration. | L16: Sustains agricultural yield and economic revenue on salt-affected land where sensitive crops fail completely. | M16: ~$50 – $250 / ha (incremental seed/planting material cost over conventional crops) | N16: Rozema & Schat (2013); WUR Adapting to Salty Conditions Report (2024); Ruto et al. (2021) | O16: =IF(fa_ECe="", "🟠 DATA NEEDED — measure soil ECe (B6)", IF(AND(ISNUMBER(fa_ECt),fa_ECe>fa_ECt), "🟢 RECOMMENDED — ECe exceeds crop threshold: switch cultivar", IF(fa_ECe>=8, "🟢 RECOMMENDED — ECe ≥ 8.0: tolerant species only", IF(fa_ECe>=4, "🟢 RECOMMENDED — ECe ≥ 4.0: moderately tolerant cultivars", "🔴 NOT RECOMMENDED — ECe < 4.0: sensitive crops still yield normally")))) -> 🟠 DATA NEEDED — measure soil ECe (B6) | P16: Not Selected
A17: 🌱 Agronomic & Biosaline Adaptation | B17: Biodrainage (Deep-Rooted Trees) | C17: Prevention / Mitigation | D17: Low to Medium budget | E17: Farm & Regional level | F17: Long term | G17: Shallow Water Table / Canal Margins | H17: Very Low (zero effluent) | I17: Low | J17: Planting rows of fast-growing, salt-tolerant trees (e.g. Eucalyptus, Poplar, Tamarix) along canals or field edges. | K17: Trees act as natural biological pumps by transpiring large volumes of shallow groundwater via deep root systems. | L17: Lowers water table depth without requiring mechanical energy or generating toxic saline effluent discharges. | M17: ~$150 – $500 / ha (saplings, planting labor, initial establishment care) | N17: Singh (2021); Qadir et al. (2014); Heuperman et al. (2002, ILRI) | O17: =IF(fa_GWD="", "🟠 DATA NEEDED — measure water table depth (B9)", IF(fa_GWD<2, "🟢 RECOMMENDED — water table < 2.0m: trees pump it down, zero effluent", "🔴 NOT RECOMMENDED — water table ≥ 2.0m: roots cannot reach it")) -> 🟠 DATA NEEDED — measure water table depth (B9) | P17: Not Selected
A18: 🌱 Agronomic & Biosaline Adaptation | B18: Microbial Bio-Inoculation (PGPR & Mycorrhizae) | C18: Mitigation / Adaptation | D18: Low budget | E18: Farm level | F18: Short term | G18: Saline / Sodic Soil Osmotic Stress | H18: Very Low (eco-friendly) | I18: Low | J18: Inoculating seeds or roots with halotolerant Plant Growth-Promoting Rhizobacteria (PGPR) and mycorrhizal fungi. | K18: Microbes produce ACC deaminase, phytohormones, and exopolysaccharides that alleviate osmotic and oxidative stress. | L18: Enhances root development, water/nutrient uptake efficiency, and crop survival under saline soil conditions. | M18: ~$30 – $120 / ha per application (commercial bio-inoculant cost) | N18: Sahab et al. (2021); Polonenko et al. (1986); Qu et al. (2015) | O18: =IF(AND(fa_ECe="",fa_SOD=""), "🟠 DATA NEEDED — measure soil ECe (B6) and Sodicity (B7)", IF(OR(AND(ISNUMBER(fa_ECe),fa_ECe>=4),AND(ISNUMBER(fa_SOD),fa_SODIC=1)), "🟢 RECOMMENDED — ECe ≥ 4.0 or SAR ≥ 13: roots are under osmotic or ionic stress", "🔵 NO-REGRET — cheap add-on, but little effect without salt stress")) -> 🟠 DATA NEEDED — measure soil ECe (B6) and Sodicity (B7) | P18: Not Selected
A19: 🌱 Agronomic & Biosaline Adaptation | B19: Summer Fallow Cover & Stubble Retention | C19: Prevention / Mitigation | D19: Low budget | E19: Farm level | F19: Short term | G19: Hot Summer Fallow / High Evaporation | H19: Very Low (crop residue only) | I19: Low | J19: Maintaining cover crops or retaining stubble/crop residues on bare soil during dry summer fallow periods. | K19: Covers bare soil from direct sunlight, reducing soil surface temperatures and evaporation rates. | L19: Prevents severe capillary salt accumulation at the surface prior to the next cropping season. | M19: ~$40 – $150 / ha (cover crop seed/planting or foregone stubble burning) | N19: Panagea et al. (2016); Stavi et al. (2021); Agronomy Review (2019) | O19: =IF(AND(fa_GWD="",fa_ECe=""), "🟠 DATA NEEDED — measure water table depth (B9) and ECe (B6)", IF(OR(AND(ISNUMBER(fa_GWD),fa_GWD<2),AND(ISNUMBER(fa_ECe),fa_ECe>=4)), "🟢 RECOMMENDED — water table < 2.0m or ECe ≥ 4.0: cover blocks capillary salt rise", "🔵 NO-REGRET — always cuts bare-soil evaporation in an arid fallow")) -> 🟠 DATA NEEDED — measure water table depth (B9) and ECe (B6) | P19: Not Selected
A20: 💧 On-Farm Water Management | B20: High-Frequency Drip Irrigation | C20: Prevention / Mitigation | D20: High budget | E20: Farm level | F20: Short term | G20: Saline Soils / Brackish Water Irrigated | H20: Low-Medium (localised leachate) | I20: Medium-High | J20: Applying frequent, small-volume water applications directly to the active crop root zone. | K20: Maintains continuously high soil water potential around the root system. | L20: Keeps soluble salts diluted in the soil solution, minimizing osmotic water stress on crops. | M20: ~$1,200 – $3,500 / ha (drip network, head control, filtration, automated valves) | N20: Karimzadeh et al. (2024); Sun et al. (2019); SWAT-Salt China Study (2025) | O20: =IF(AND(fa_ECe="",fa_ECw=""), "🟠 DATA NEEDED — measure soil ECe (B6) and irrigation ECw (B8)", IF(OR(AND(ISNUMBER(fa_ECe),fa_ECe>=4),AND(ISNUMBER(fa_ECw),fa_ECw>=0.7)), "🟢 RECOMMENDED — ECe ≥ 4.0 or ECw ≥ 0.7: frequent wetting keeps the root zone diluted", "🔴 NOT RECOMMENDED — no salt load: standard scheduling is enough")) -> 🟠 DATA NEEDED — measure soil ECe (B6) and irrigation ECw (B8) | P20: Not Selected
A21: 💧 On-Farm Water Management | B21: Conjunctive Water Use (Blending / Cyclic Use) | C21: Mitigation / Adaptation | D21: Low to Medium budget | E21: Farm level | F21: Short term | G21: Fresh Water Scarcity + Brackish Source | H21: Low-Medium (blended salt load) | I21: Medium | J21: Strategically blending or alternating fresh surface water and brackish groundwater based on crop sensitivity stage. | K21: Fresh water is prioritized during sensitive germination/seedling stages; brackish water is used during tolerant stages. | L21: Extends limited fresh water supplies while avoiding acute salt damage during critical growth stages. | M21: ~$100 – $400 / ha (dual manifold/mixing valves or management costs) | N21: Sharma & Rao (1998); Khajanchi & Meena (2008); Singh (2021) | O21: =IF(fa_ECw="", "🟠 DATA NEEDED — measure irrigation water ECw (B8)", IF(fa_ECw>=1.5, "🟢 RECOMMENDED — ECw ≥ 1.5 dS/m: worth blending or cycling with a fresher source", "🔴 NOT RECOMMENDED — ECw < 1.5 dS/m: fresh supply, nothing to blend")) -> 🟠 DATA NEEDED — measure irrigation water ECw (B8) | P21: Not Selected
A22: 💧 On-Farm Water Management | B22: Rainwater Harvesting & Managed Infiltration | C22: Prevention / Mitigation | D22: Medium budget | E22: Farm level | F22: Medium term | G22: Seasonal Rainfall Areas | H22: Very Low (fresh water only) | I22: Low-Medium | J22: Capturing seasonal rainfall via farm ponds, contour bunds, or infiltration trenches. | K22: Collects runoff and directs fresh rainwater into the soil profile to recharge local freshwater lenses. | L22: Provides natural, cost-free salt leaching and creates a protective fresh groundwater buffer. | M22: ~$200 – $1,500 / ha (earthworks, farm pond excavation, bunding) | N22: FAO Water Reports; UNEP World Atlas of Desertification; Singh (2021) | O22: =IF(fa_ECw="", "🟠 DATA NEEDED — measure irrigation water ECw (B8)", IF(fa_ECw>=0.7, "🟢 RECOMMENDED — ECw ≥ 0.7 dS/m: harvested rainwater dilutes a brackish supply", "🔵 NO-REGRET — builds a fresh water buffer for the dry season")) -> 🟠 DATA NEEDED — measure irrigation water ECw (B8) | P22: Not Selected
A23: 💧 On-Farm Water Management | B23: Controlled Drainage & Water Table Management | C23: Prevention / Mitigation | D23: Low to Medium budget | E23: Farm level | F23: Medium term | G23: Subsurface Drained Croplands | H23: Low (reduces effluent volume) | I23: Low-Medium | J23: Installing adjustable water level control structures on subsurface drain outlets. | K23: Regulates drainage outflow: holds back fresh water during dry spells and opens outlets during leaching events. | L23: Reduces total drain outflow volume and nutrient/salt export by 30–50% while conserving shallow soil moisture. | M23: ~$300 – $800 / ha (control structure hardware retrofitted on drain outlets) | N23: Ritzema et al. (2023); Shedekar et al. (2025); DRAINMOD research | O23: =IF(fa_GWD="", "🟠 DATA NEEDED — measure water table depth (B9)", IF(fa_GWD<2, "🟢 RECOMMENDED — water table < 2.0m: regulate outflow, cut effluent volume", "🔵 NO-REGRET — only if subsurface drains are already installed")) -> 🟠 DATA NEEDED — measure water table depth (B9) | P23: Not Selected
A24: 🌐 Regional & Nature-Based Solutions | B24: Aquifer Storage and Recovery (ASR) | C24: Prevention / Mitigation | D24: High budget | E24: Regional / National level | F24: Long term | G24: Coastal / Inland Brackish Aquifers | H24: Low (aquifer injection permit) | I24: High | J24: Injecting surplus winter surface water or treated rainwater into deep brackish aquifers via injection wells. | K24: Forms an underground 'freshwater bubble' within a saline aquifer, stored without evaporation loss. | L24: Provides strategic seasonal freshwater storage for extraction during peak summer drought/irrigation periods. | M24: ~$100,000 – $500,000+ per ASR well site (~$1,500–$4,000 / ha serviced capital cost) | N24: Acacia Water (2024); WUR Adapting to Salty Conditions (2024); Pyne (2005) | O24: =IF(fa_ECw="", "🟠 DATA NEEDED — measure irrigation water ECw (B8)", IF(fa_ECw>=0.7, "🟢 RECOMMENDED — ECw ≥ 0.7 dS/m: store winter surplus to dilute the summer supply", "🔵 NO-REGRET — regional seasonal storage; needs a confined aquifer")) -> 🟠 DATA NEEDED — measure irrigation water ECw (B8) | P24: Not Selected
O25: Reset control has moved to the Dashboard (cell K2).

Sheet Section D - Classification 2
A1: SECTION B: CLASSIFICATION CRITERIA — WHAT EVERY CLASS IN THIS SHEET MEANS
A2: Variable | B2: Class as used in this sheet | C2: Definition & threshold | E2: What it means when you use it
A3: 🎯 Strategic Goal | B3: Prevention | C3: Stops salinization before it becomes a problem. | E3: Triggered when the drivers are present (seepage, shallow water table, poor water quality) but the soil is still healthy.
A4: 🎯 Strategic Goal | B4: Mitigation | C4: Reduces the rate or severity of ongoing salinization. | E4: Triggered when salt is accumulating but the field is still productive.
A5: 🎯 Strategic Goal | B5: Remediation | C5: Restores soil that is already saline or sodic. | E5: Triggered once ECe ≥ 4 dS/m or SAR ≥ 13 has actually been measured.
A6: 🎯 Strategic Goal | B6: Adaptation | C6: Works with the salinity that is there instead of removing it. | E6: Triggered when reclamation is not affordable or not physically possible.
A7: 💰 Budget Class | B7: Low budget | C7: < $250 / ha — indicative capital plus first-year operation, taken from column M. | E7: Fits an existing farm operating budget: consumables and light field work, no new equipment.
A8: 💰 Budget Class | B8: Low to Medium budget | C8: $250 – $750 / ha. | E8: Contracted machinery or bulk inputs; still a farm-level operating decision.
A9: 💰 Budget Class | B9: Medium budget | C9: $750 – $2,000 / ha. | E9: On-farm capital investment that has to be depreciated over several seasons.
A10: 💰 Budget Class | B10: High budget | C10: > $2,000 / ha, or any off-farm capital work (canals, well fields, ASR sites). | E10: Needs project or public financing; not a decision a single grower can take.
A11: 📍 Spatial Scale | B11: Farm level | C11: Applied inside one holding. | E11: The grower decides and pays; no coordination needed.
A12: 📍 Spatial Scale | B12: Farm & Regional level | C12: Works at farm scale but only pays off when neighbours do the same. | E12: Needs at least informal coordination along a canal or a water-table unit.
A13: 📍 Spatial Scale | B13: Regional / National level | C13: Shared infrastructure or policy. | E13: Requires a water board, authority or ministry; long lead time and permits.
... A34: 🏗️ Category | B34: 🌐 Regional & Nature-Based Solutions | C34: Storage, recharge and landscape-scale measures. | E34: Changes the regional water balance; needs an authority to carry it.
A36: SECTION C: DECISION LOGIC — WHICH INPUT DECIDES EACH MEASURE, AND AT WHICH THRESHOLD IT FLIPS
A37: Measure | B37: Deciding input (cell on ‘1. Field Protocol’) | C37: 🟢 RECOMMENDED when | D37: 🟠 DATA NEEDED when | E37: 🔴 NOT RECOMMENDED / UNSAFE when | F37: Where the threshold comes from
A38: ='Section C - Measure Selection'!B4 -> Subsurface Pipe Drainage (SPD) | B38: Water table depth (B9); Soil ECe (B6) | C38: Water table < 2.0 m, or ECe ≥ 4.0 dS/m — leachate needs somewhere to go. | D38: B9 and B6 both empty. | E38: Water table ≥ 2.0 m and ECe < 4.0: no drainage constraint to solve. | F38: 2.0 m is the depth above which capillary rise reaches the root zone (Ritzema 1994; Wang et al. 2022). ECe 4.0 dS/m is the USDA saline boundary (Richards 1954).
A39: ='Section C - Measure Selection'!B5 -> Open Ditch Drainage | B39: Water table depth (B9) | C39: Water table < 2.0 m — gravity drainage as the low-cost alternative to SPD. | D39: B9 empty. | E39: Water table ≥ 2.0 m: nothing to drain. | F39: Same 2.0 m capillary threshold as SPD (Tanji & Kielen 2002; Singh 2019).
A40: ='Section C - Measure Selection'!B6 -> Vertical Drainage / Tubewells | B40: Water table depth (B9) | C40: Water table < 1.5 m — severe regional waterlogging only. | D40: B9 empty. | E40: Water table ≥ 1.5 m: regional pumping cannot be justified. | F40: Tighter than farm drainage because energy cost is continuous (Qadir et al. 2014; Pakistan SCARP review).
A41: ='Section C - Measure Selection'!B7 -> Canal Lining | B41: Water table depth (B9) | C41: Water table < 2.0 m — a rising table points to canal or field seepage. | D41: B9 empty. | E41: Never red. Falls back to 🔵 NO-REGRET at ≥ 2.0 m: preventive, never harmful. | F41: Canal seepage is the dominant driver of regional water-table rise in dryland schemes (Wichelns 1999; Singh 2021).
A42: ='Section C - Measure Selection'!B8 -> Deep Ripping / DVRT (Deep Vertical Rotary Tillage) | B42: Soil pH (B5); SAR (B7) | C42: SAR ≥ 13 — a dispersed crust and pan are likely. pH alone never triggers it. | D42: B5 and B7 both empty; or pH ≥ 8.5 without SAR (pH alone is not conclusive). | E42: Never red. Falls back to 🔵 NO-REGRET: worth doing only if a pan is confirmed by field inspection. | F42: SAR 13 / pH 8.5 sodic boundary (Richards 1954). Pan depth itself is not an input in this model.
A43: ='Section C - Measure Selection'!B9 -> Precision Land Leveling (Laser Grading) | B43: Micro-topography & slope (B12) | C43: Elevation spread ≥ 5 cm across the field. | D43: B12 empty — the survey has not been done. | E43: Never red. Falls back to 🔵 NO-REGRET below 5 cm: re-check every 3–5 years. | F43: 5 cm is the practical limit for uniform surface irrigation (Rhoades et al. 1992; Ashraf & Saeed 2006). Added in v7 — v6 had no threshold here at all.
A44: ='Section C - Measure Selection'!B10 -> Forced Leaching Regime | B44: pH (B5); SAR (B7); ECe (B6) | C44: ECe ≥ 4.0 dS/m and the soil is not sodic. | D44: ECe empty while the soil is not sodic; or ECe ≥ 4.0 while sodicity is not measured. | E44: 🔴 UNSAFE NOW if SAR ≥ 13, or if SAR is missing and pH > 8.5 (precaution) — the leaching trap outranks every other outcome. NOT RECOMMENDED if ECe < 4.0: no salt load, wasted water. | F44: Flushing a sodic soil before adding calcium collapses the structure (Qadir et al. 2007; Van Hoorn & Van Alphen 1994).
A45: ='Section C - Measure Selection'!B11 -> Gypsum Application (CaSO4·2H2O) | B45: Soil pH (B5); SAR (B7) | C45: SAR ≥ 13 — sodium has to be displaced before any leaching. PROVISIONAL if SAR is missing and pH > 8.5 (pH is not an official criterion). | D45: B5 and B7 both empty; or SAR missing and pH ≤ 8.5 (pH cannot show whether the soil is sodic). | E45: SAR < 13 measured, whatever the pH: gypsum only adds salt to a non-sodic soil. | F45: Richards (1954); Qadir et al. (2007). Dose still needs CEC (B13) and bulk density (B14).
A46: ='Section C - Measure Selection'!B12 -> Soil Acidification (Elemental Sulfur / Acid Injection) | B46: Soil pH (B5); Native lime % (B17) | C46: SAR ≥ 13 measured, pH ≥ 8.5 and native lime > 0 % — acid frees the calcium already in the soil. | D46: pH empty; or pH ≥ 8.5 with lime unmeasured; or SAR not measured (gypsum is then the provisional option). | E46: pH < 8.5: no carbonate alkalinity to neutralise. Lime = 0 %: nothing to dissolve, use gypsum instead. SAR < 13 measured: the soil is not sodic. | F46: Acid only releases Ca²⁺ where CaCO₃ is present (Qadir et al. 2007; Litalien & Zeeb 2020).
A47: ='Section C - Measure Selection'!B13 -> Organic Amendments (Compost, Manure, Biochar) | B47: pH (B5); ECe (B6); SAR (B7) | C47: SAR ≥ 13, or ECe ≥ 4.0 dS/m — buffers osmotic stress and rebuilds structure. | D47: All three empty. | E47: Never red. Falls back to 🔵 NO-REGRET: raises CEC and water holding capacity in any soil. | F47: Setia et al. (2013); Sun et al. (2019); Amelung et al. (2020).
A48: ='Section C - Measure Selection'!B14 -> Irrigation Water Acidification | B48: RSC (B16); ECw (B8) as proxy | C48: RSC > 2.5 meq/L — a real bicarbonate hazard. | D48: RSC and ECw both empty; or RSC empty while ECw ≥ 0.7 (confirm with an RSC analysis). | E48: RSC ≤ 2.5 meq/L; or ECw < 0.7 dS/m with no RSC measured: fresh water, no hazard. | F48: RSC 2.5 meq/L hazard boundary (Ayers & Westcot 1985; Doneen 1954). Changed in v7 — v6 judged this on ECw, which measures salinity, not bicarbonate.
A49: ='Section C - Measure Selection'!B15 -> Mulched Drip Irrigation (MDI) | B49: ECe (B6); ECw (B8) | C49: ECe ≥ 4.0 dS/m, or ECw ≥ 0.7 dS/m — there is a salt load to keep off the surface. | D49: B6 and B8 both empty. | E49: Never red. Falls back to 🔵 NO-REGRET: still saves water in an arid climate. | F49: ECw 0.7 dS/m is the FAO ‘slight restriction’ boundary (Ayers & Westcot 1985); Wang et al. (2018).
... A58: ='Section C - Measure Selection'!B24 -> Aquifer Storage and Recovery (ASR) | B58: Irrigation water ECw (B8) | C58: ECw ≥ 0.7 dS/m — store winter surplus to dilute the summer supply. | D58: B8 empty. | E58: Never red. Falls back to 🔵 NO-REGRET: regional storage still needs a confined aquifer. | F58: Ayers & Westcot (1985); ASR feasibility depends on aquifer confinement, not recorded here.
